Workbook

Sheet README
A1: SaaS company reference model
A2: Reference model for the block model builder (acceptance test). Company-level, quarterly, 32 periods from 2027-01-01.
A3: All figures are illustrative. It describes a generic subscription software company, not a real one.
A5: Sheets
A6: Timeline: timeline settings and per-period built-ins (t, period_start, period_end, year).
A7: Drivers: scalar assumptions; each value cell is a defined name equal to its id. 'series' means see Driver_Series.
A8: Driver_Series: time-varying drivers, one row per id.
A9: Calculations: one row per derived line in dependency order. Column F is the DSL formula; the cells are the same logic as live Excel formulas.
A10: Annual: fiscal-year rollups via annual().
A11: Expected / Expected_Annual: acceptance outputs, linked live to Calculations and Annual. Compare at relative tolerance 1e-6.
A12: Report: lines for the exported summary worksheet, in order, with display format (values linked for preview).
A14: Layout on period sheets
... A23: See the accompanying notes file for the narrative, sources, simplifications and new functions needed.

Sheet Timeline
A1: id | B1: value | C1: notes
A2: start_date | B2: 46388 | C2: First day of period 1.
A3: frequency | B3: quarter | C3: Period length.
A4: periods | B4: 32 | C4: Number of periods.
A5: months_per_period | B5: 3 | C5: Follows from frequency (quarter = 3).
A6: fiscal_year_end | B6: 12-31 | C6: Fiscal year equals calendar year.
A8: Per-period built-ins (columns J onward are periods)
A9: t | J9: 1 | K9: =J9+1 -> 2 | L9: =K9+1 -> 3 | M9: =L9+1 -> 4 | N9: =M9+1 -> 5 | O9: =N9+1 -> 6 | P9: =O9+1 -> 7 | Q9: =P9+1 -> 8 | R9: =Q9+1 -> 9 | ... AO9: =AN9+1 -> 32
A10: period_start | J10: =start_date -> 46388 | K10: =EDATE(J10,months_per_period) -> 46478 | L10: =EDATE(K10,months_per_period) -> 46569 | M10: =EDATE(L10,months_per_period) -> 46661 | N10: =EDATE(M10,months_per_period) -> 46753 | O10: =EDATE(N10,months_per_period) -> 46844 | P10: =EDATE(O10,months_per_period) -> 46935 | Q10: =EDATE(P10,months_per_period) -> 47027 | R10: =EDATE(Q10,months_per_period) -> 47119 | ... AO10: =EDATE(AN10,months_per_period) -> 49218
A11: period_end | J11: =EDATE(J10,months_per_period)-1 -> 46477 | K11: =EDATE(K10,months_per_period)-1 -> 46568 | L11: =EDATE(L10,months_per_period)-1 -> 46660 | M11: =EDATE(M10,months_per_period)-1 -> 46752 | N11: =EDATE(N10,months_per_period)-1 -> 46843 | O11: =EDATE(O10,months_per_period)-1 -> 46934 | P11: =EDATE(P10,months_per_period)-1 -> 47026 | Q11: =EDATE(Q10,months_per_period)-1 -> 47118 | ... AO11: =EDATE(AO10,months_per_period)-1 -> 49309
A12: year | J12: =YEAR(J11) -> 2027 | K12: =YEAR(K11) -> 2027 | L12: =YEAR(L11) -> 2027 | M12: =YEAR(M11) -> 2027 | N12: =YEAR(N11) -> 2028 | O12: =YEAR(O11) -> 2028 | P12: =YEAR(P11) -> 2028 | Q12: =YEAR(Q11) -> 2028 | ... AO12: =YEAR(AO11) -> 2034
A13: label | J13: =YEAR(J10)&"Q"&ROUNDUP(MONTH(J10)/3,0) -> 2027Q1 | K13: =YEAR(K10)&"Q"&ROUNDUP(MONTH(K10)/3,0) -> 2027Q2 | L13: =YEAR(L10)&"Q"&ROUNDUP(MONTH(L10)/3,0) -> 2027Q3 | M13: =YEAR(M10)&"Q"&ROUNDUP(MONTH(M10)/3,0) -> 2027Q4 | N13: =YEAR(N10)&"Q"&ROUNDUP(MONTH(N10)/3,0) -> 2028Q1 | O13: =YEAR(O10)&"Q"&ROUNDUP(MONTH(O10)/3,0) -> 2028Q2 | P13: =YEAR(P10)&"Q"&ROUNDUP(MONTH(P10)/3,0) -> 2028Q3 | Q13: =YEAR(Q10)&"Q"&ROUNDUP(MONTH(Q10)/3,0) -> 2028Q4 | ... AO13: =YEAR(AO10)&"Q"&ROUNDUP(MONTH(AO10)/3,0) -> 2034Q4

Sheet Drivers
A1: id | B1: label | C1: group | D1: type | E1: unit | F1: value | G1: low | H1: high | I1: source | J1: notes
A2: opening_customers | B2: Customers at start of period 1 | C2: Customers | D2: quantity | E2: customers | F2: 400 | I2: illustrative
A3: marketing_spend | B3: Marketing spend | C3: Customers | D3: series<currency> | E3: USD | F3: series | I3: illustrative | J3: Paid acquisition, events and content, per quarter.
A4: marketing_cost_per_customer | B4: Marketing cost per new customer | C4: Customers | D4: currency | E4: USD/customer | F4: 15000 | G4: 10000 | H4: 22000 | I4: illustrative | J4: Marketing spend needed to win one customer; sales team cost is separate.
A5: sales_reps | B5: Quota-carrying sales reps | C5: Customers | D5: series<count> | E5: FTE | F5: series | I5: illustrative
A6: deals_per_rep_q | B6: Deals each rep can close per quarter | C6: Customers | D6: float | E6: customers/FTE | F6: 10 | G6: 7 | H6: 14 | I6: illustrative | J6: Caps new customers when the sales team, not marketing, is the constraint.
A7: churn_rate_q | B7: Quarterly customer churn | C7: Customers | D7: percent | E7: fraction | F7: 0.04 | G7: 0.02 | H7: 0.07 | I7: illustrative | J7: Share of customers at the start of a quarter who cancel during it.
A8: arpa_monthly | B8: Average revenue per account (monthly) | C8: Pricing | D8: currency | E8: USD/customer | F8: 2000 | G8: 1500 | H8: 2600 | I8: illustrative | J8: List price net of discounts, per customer per month, in period 1.
A9: price_growth_annual | B9: Annual price increase | C9: Pricing | D9: percent | E9: fraction | F9: 0.03 | G9: 0 | H9: 0.06 | I9: illustrative
A10: months_per_quarter | B10: Months per quarter | C10: Pricing | D10: float | E10: months | F10: 3 | I10: illustrative | J10: Convention.
A11: months_per_year | B11: Months per year | C11: Pricing | D11: float | E11: months | F11: 12 | I11: illustrative | J11: Convention.
A12: hosting_cost_monthly | B12: Hosting cost per customer (monthly) | C12: Cost of revenue | D12: currency | E12: USD/customer | F12: 140 | G12: 100 | H12: 200 | I12: illustrative | J12: Cloud infrastructure and third-party services per customer per month.
A13: support_cost_pct | B13: Customer support cost | C13: Cost of revenue | D13: percent | E13: fraction of revenue | F13: 0.06 | I13: illustrative
A14: payment_fees_pct | B14: Payment processing fees | C14: Cost of revenue | D14: percent | E14: fraction of revenue | F14: 0.025 | I14: illustrative
A15: sales_rep_cost_q | B15: Loaded cost per sales rep | C15: Operating expenses | D15: currency | E15: USD/FTE | F15: 45000 | I15: illustrative | J15: Salary, commission and benefits per quarter.
A16: engineers | B16: Engineering headcount | C16: Operating expenses | D16: series<count> | E16: FTE | F16: series | I16: illustrative
A17: engineer_cost_q | B17: Loaded cost per engineer | C17: Operating expenses | D17: currency | E17: USD/FTE | F17: 55000 | I17: illustrative | J17: Per quarter.
A18: ga_headcount | B18: G&A headcount | C18: Operating expenses | D18: series<count> | E18: FTE | F18: series | I18: illustrative | J18: Finance, people, legal and operations.
A19: ga_cost_per_fte_q | B19: Loaded cost per G&A employee | C19: Operating expenses | D19: currency | E19: USD/FTE | F19: 40000 | I19: illustrative | J19: Per quarter.
A20: other_opex_initial_q | B20: Other operating costs, period 1 | C20: Operating expenses | D20: currency | E20: USD | F20: 600000 | I20: illustrative | J20: Rent, software and professional fees.
A21: other_opex_growth_q | B21: Other operating cost growth per quarter | C21: Operating expenses | D21: percent | E21: fraction | F21: 0.025 | I21: illustrative
A22: platform_rebuild_cost | B22: Platform rebuild (one-time) | C22: Operating expenses | D22: currency | E22: USD | F22: 6000000 | I22: illustrative | J22: A one-time re-architecture project, expensed as incurred.
A23: platform_rebuild_start | B23: Platform rebuild start period | C23: Operating expenses | D23: int | E23: period | F23: 9 | I23: illustrative
A24: platform_rebuild_periods | B24: Platform rebuild duration | C24: Operating expenses | D24: int | E24: quarters | F24: 4 | I24: illustrative
A25: growth_capex | B25: Growth capex | C25: Capex | D25: series<currency> | E25: USD | F25: series | I25: illustrative | J25: Office fit-outs and equipment for new hires.
A26: maintenance_capex_pct | B26: Maintenance capex | C26: Capex | D26: percent | E26: fraction of revenue | F26: 0.015 | I26: illustrative
A27: asset_life_q | B27: Depreciable life | C27: Capex | D27: int | E27: quarters | F27: 12 | I27: illustrative | J27: Straight line, no salvage.
A28: ar_days | B28: Receivable days | C28: Financing | D28: float | E28: days | F28: 45 | I28: illustrative
A29: ap_days | B29: Payable days | C29: Financing | D29: float | E29: days | F29: 30 | I29: illustrative
A30: days_per_quarter | B30: Days per quarter | C30: Financing | D30: float | E30: days | F30: 91.25 | I30: illustrative | J30: Convention.
A31: annual_prepay_share | B31: Revenue billed annually in advance | C31: Financing | D31: percent | E31: fraction of revenue | F31: 0.4 | I31: illustrative | J31: Annual contracts billed up front create deferred revenue.
A32: prepaid_quarters | B32: Average quarters of service prepaid | C32: Financing | D32: float | E32: quarters | F32: 1.5 | I32: illustrative | J32: Half of a year's billing, on average, is still unearned at quarter end.
A33: tax_rate | B33: Blended income tax rate | C33: Financing | D33: percent | E33: fraction | F33: 0.25 | I33: illustrative | J33: Losses carried forward without limit or expiry.
A34: opening_cash | B34: Opening cash, start of period 1 | C34: Financing | D34: currency | E34: USD | F34: 25000000 | I34: illustrative
A35: equity_raises | B35: Equity raised | C35: Financing | D35: series<currency> | E35: USD | F35: series | I35: illustrative | J35: Scheduled raises; no cash-triggered financing (that would be circular).
A36: min_cash_balance | B36: Minimum cash balance | C36: Financing | D36: currency | E36: USD | F36: 8000000 | I36: illustrative | J36: Used only for the cash check flag.
A37: discount_rate_annual | B37: Discount rate (annual) | C37: Valuation | D37: percent | E37: fraction | F37: 0.18 | G37: 0.12 | H37: 0.25 | I37: illustrative | J37: Growth-stage rate on unlevered FCF.
A38: terminal_growth_annual | B38: Terminal growth (annual) | C38: Valuation | D38: percent | E38: fraction | F38: 0.03 | G38: 0 | H38: 0.05 | I38: illustrative
A39: irr_guess_q | B39: IRR solver starting guess (quarterly) | C39: Valuation | D39: percent | E39: fraction | F39: 0.05 | I39: illustrative | J39: Only chooses between roots; does not change a unique answer.
A40: terminal_period | B40: Terminal period | C40: Valuation | D40: int | E40: period | F40: 32 | I40: illustrative | J40: Equals the number of periods.

Sheet Driver_Series
A1: id | B1: label | C1: group | D1: type | E1: unit | F1: source | G1: notes | I1: scalar | J1: 1 | K1: 2 | L1: 3 | M1: 4 | N1: 5 | O1: 6 | P1: 7 | Q1: 8 | R1: 9 | S1: 10 | T1: 11 | U1: 12 | V1: 13 | W1: 14 | X1: 15 | Y1: 16 | Z1: 17 | AA1: 18 | AB1: 19 | AC1: 20 | AD1: 21 | AE1: 22 | AF1: 23 | AG1: 24 | AH1: 25 | AI1: 26 | AJ1: 27 | AK1: 28 | AL1: 29 | AM1: 30 | AN1: 31 | AO1: 32
A2: period label → | J2: =Timeline!J$13 -> 2027Q1 | K2: =Timeline!K$13 -> 2027Q2 | L2: =Timeline!L$13 -> 2027Q3 | M2: =Timeline!M$13 -> 2027Q4 | N2: =Timeline!N$13 -> 2028Q1 | O2: =Timeline!O$13 -> 2028Q2 | P2: =Timeline!P$13 -> 2028Q3 | Q2: =Timeline!Q$13 -> 2028Q4 | ... AO2: =Timeline!AO$13 -> 2034Q4
A3: marketing_spend | B3: Marketing spend | C3: Customers | D3: series<currency> | E3: USD | F3: illustrative | G3: see Drivers | J3: 600000 | K3: 700000 | L3: 800000 | M3: 900000 | N3: 1000000 | O3: 1100000 | P3: 1200000 | Q3: 1300000 | R3: 1400000 | S3: 1500000 | T3: 1600000 | U3: 1700000 | V3: 1800000 | W3: 1900000 | X3: 2000000 | Y3: 2100000 | Z3: 2200000 | AA3: 2260000 | AB3: 2320000 | AC3: 2380000 | AD3: 2440000 | AE3: 2500000 | AF3: 2560000 | AG3: 2620000 | AH3: 2680000 | AI3: 2740000 | AJ3: 2800000 | AK3: 2860000 | AL3: 2920000 | AM3: 2980000 | AN3: 3040000 | AO3: 3100000
A4: sales_reps | B4: Quota-carrying sales reps | C4: Customers | D4: series<count> | E4: FTE | F4: illustrative | G4: see Drivers | J4: 6 | K4: 6 | L4: 7 | M4: 8 | N4: 9 | O4: 10 | P4: 11 | Q4: 12 | R4: 13 | S4: 14 | T4: 15 | U4: 16 | V4: 17 | W4: 18 | X4: 19 | Y4: 20 | Z4: 21 | AA4: 21 | AB4: 22 | AC4: 22 | AD4: 23 | AE4: 23 | AF4: 24 | AG4: 24 | AH4: 25 | AI4: 25 | AJ4: 26 | AK4: 26 | AL4: 27 | AM4: 27 | AN4: 28 | AO4: 28
A5: engineers | B5: Engineering headcount | C5: Operating expenses | D5: series<count> | E5: FTE | F5: illustrative | G5: see Drivers | J5: 20 | K5: 21 | L5: 22 | M5: 24 | N5: 26 | O5: 28 | P5: 30 | Q5: 32 | R5: 34 | S5: 36 | T5: 38 | U5: 40 | V5: 41 | W5: 42 | X5: 43 | Y5: 44 | Z5: 45 | AA5: 46 | AB5: 47 | AC5: 48 | AD5: 49 | AE5: 50 | AF5: 51 | AG5: 52 | AH5: 53 | AI5: 54 | AJ5: 55 | AK5: 56 | AL5: 57 | AM5: 58 | AN5: 59 | AO5: 60
A6: ga_headcount | B6: G&A headcount | C6: Operating expenses | D6: series<count> | E6: FTE | F6: illustrative | G6: see Drivers | J6: 6 | K6: 6 | L6: 6 | M6: 6 | N6: 8 | O6: 8 | P6: 8 | Q6: 8 | R6: 10 | S6: 10 | T6: 10 | U6: 10 | V6: 12 | W6: 12 | X6: 12 | Y6: 12 | Z6: 14 | AA6: 14 | AB6: 14 | AC6: 14 | AD6: 15 | AE6: 15 | AF6: 15 | AG6: 15 | AH6: 16 | AI6: 16 | AJ6: 16 | AK6: 16 | AL6: 17 | AM6: 17 | AN6: 17 | AO6: 17
A7: growth_capex | B7: Growth capex | C7: Capex | D7: series<currency> | E7: USD | F7: illustrative | G7: see Drivers | J7: 400000 | K7: 400000 | L7: 400000 | M7: 400000 | N7: 250000 | O7: 250000 | P7: 250000 | Q7: 250000 | R7: 900000 | S7: 900000 | T7: 900000 | U7: 900000 | V7: 300000 | W7: 300000 | X7: 300000 | Y7: 300000 | Z7: 300000 | AA7: 300000 | AB7: 300000 | AC7: 300000 | AD7: 300000 | AE7: 300000 | AF7: 300000 | AG7: 300000 | AH7: 300000 | AI7: 300000 | AJ7: 300000 | AK7: 300000 | AL7: 300000 | AM7: 300000 | AN7: 300000 | AO7: 300000
A8: equity_raises | B8: Equity raised | C8: Financing | D8: series<currency> | E8: USD | F8: illustrative | G8: see Drivers | J8: 0 | K8: 0 | L8: 0 | M8: 0 | N8: 0 | O8: 30000000 | P8: 0 | Q8: 0 | R8: 0 | S8: 0 | T8: 0 | U8: 0 | V8: 0 | W8: 40000000 | X8: 0 | Y8: 0 | Z8: 0 | AA8: 0 | AB8: 0 | AC8: 0 | AD8: 0 | AE8: 0 | AF8: 0 | AG8: 0 | AH8: 0 | AI8: 0 | AJ8: 0 | AK8: 0 | AL8: 0 | AM8: 0 | AN8: 0 | AO8: 0

Sheet Calculations
A1: id | B1: label | C1: group | D1: type | E1: unit | F1: formula | G1: excel_ref | H1: notes | I1: scalar | J1: 1 | K1: 2 | L1: 3 | M1: 4 | N1: 5 | O1: 6 | P1: 7 | Q1: 8 | R1: 9 | S1: 10 | T1: 11 | U1: 12 | V1: 13 | W1: 14 | X1: 15 | Y1: 16 | Z1: 17 | AA1: 18 | AB1: 19 | AC1: 20 | AD1: 21 | AE1: 22 | AF1: 23 | AG1: 24 | AH1: 25 | AI1: 26 | AJ1: 27 | AK1: 28 | AL1: 29 | AM1: 30 | AN1: 31 | AO1: 32
A2: period label → | J2: =Timeline!J$13 -> 2027Q1 | K2: =Timeline!K$13 -> 2027Q2 | L2: =Timeline!L$13 -> 2027Q3 | M2: =Timeline!M$13 -> 2027Q4 | N2: =Timeline!N$13 -> 2028Q1 | O2: =Timeline!O$13 -> 2028Q2 | P2: =Timeline!P$13 -> 2028Q3 | Q2: =Timeline!Q$13 -> 2028Q4 | ... AO2: =Timeline!AO$13 -> 2034Q4
A3: new_customers_from_marketing | B3: New customers marketing can win | C3: Customers | D3: series<count> | E3: customers | F3: round(marketing_spend / marketing_cost_per_customer, 0) | G3: Calculations!J3:AO3 | H3: Round half away from zero (Excel convention). | J3: =ROUND((Driver_Series!J3/marketing_cost_per_customer),0) -> 40 | K3: =ROUND((Driver_Series!K3/marketing_cost_per_customer),0) -> 47 | L3: =ROUND((Driver_Series!L3/marketing_cost_per_customer),0) -> 53 | M3: =ROUND((Driver_Series!M3/marketing_cost_per_customer),0) -> 60 | N3: =ROUND((Driver_Series!N3/marketing_cost_per_customer),0) -> 67 | O3: =ROUND((Driver_Series!O3/marketing_cost_per_customer),0) -> 73 | P3: =ROUND((Driver_Series!P3/marketing_cost_per_customer),0) -> 80 | Q3: =ROUND((Driver_Series!Q3/marketing_cost_per_customer),0) -> 87 | ... AO3: =ROUND((Driver_Series!AO3/marketing_cost_per_customer),0) -> 207
A4: sales_capacity | B4: New customers the sales team can close | C4: Customers | D4: series<quantity> | E4: customers | F4: sales_reps * deals_per_rep_q | G4: Calculations!J4:AO4 | J4: =(Driver_Series!J4*deals_per_rep_q) -> 60 | K4: =(Driver_Series!K4*deals_per_rep_q) -> 60 | L4: =(Driver_Series!L4*deals_per_rep_q) -> 70 | M4: =(Driver_Series!M4*deals_per_rep_q) -> 80 | N4: =(Driver_Series!N4*deals_per_rep_q) -> 90 | O4: =(Driver_Series!O4*deals_per_rep_q) -> 100 | P4: =(Driver_Series!P4*deals_per_rep_q) -> 110 | Q4: =(Driver_Series!Q4*deals_per_rep_q) -> 120 | ... AO4: =(Driver_Series!AO4*deals_per_rep_q) -> 280
A5: new_customers | B5: New customers | C5: Customers | D5: series<quantity> | E5: customers | F5: min(new_customers_from_marketing, sales_capacity) | G5: Calculations!J5:AO5 | H5: The tighter of marketing and sales capacity. | J5: =MIN(J3,J4) -> 40 | K5: =MIN(K3,K4) -> 47 | L5: =MIN(L3,L4) -> 53 | M5: =MIN(M3,M4) -> 60 | N5: =MIN(N3,N4) -> 67 | O5: =MIN(O3,O4) -> 73 | P5: =MIN(P3,P4) -> 80 | Q5: =MIN(Q3,Q4) -> 87 | ... AO5: =MIN(AO3,AO4) -> 207
A6: retention_factor | B6: Share of a period-1 customer still active | C6: Customers | D6: series<float> | E6: fraction | F6: growth(1 - churn_rate_q, 0 - churn_rate_q) | G6: Calculations!J6:AO6 | H6: (1 - churn) to the power t. | J6: =((1-churn_rate_q))*(1+(0-churn_rate_q))^(Timeline!J$9-1) -> 0.96 | K6: =((1-churn_rate_q))*(1+(0-churn_rate_q))^(Timeline!K$9-1) -> 0.9216 | L6: =((1-churn_rate_q))*(1+(0-churn_rate_q))^(Timeline!L$9-1) -> 0.884736 | M6: =((1-churn_rate_q))*(1+(0-churn_rate_q))^(Timeline!M$9-1) -> 0.84934656 | N6: =((1-churn_rate_q))*(1+(0-churn_rate_q))^(Timeline!N$9-1) -> 0.8153727 | O6: =((1-churn_rate_q))*(1+(0-churn_rate_q))^(Timeline!O$9-1) -> 0.78275779 | P6: =((1-churn_rate_q))*(1+(0-churn_rate_q))^(Timeline!P$9-1) -> 0.75144748 | Q6: =((1-churn_rate_q))*(1+(0-churn_rate_q))^(Timeline!Q$9-1) -> 0.72138958 | ... AO6: =((1-churn_rate_q))*(1+(0-churn_rate_q))^(Timeline!AO$9-1) -> 0.2708192
A7: new_customers_scaled | B7: New customers scaled by retention | C7: Customers | D7: series<quantity> | E7: customers | F7: new_customers / retention_factor | G7: Calculations!J7:AO7 | H7: Helper for the closed-form customer count below. | J7: =(J5/J6) -> 41.666667 | K7: =(K5/K6) -> 50.998264 | L7: =(L5/L6) -> 59.904876 | M7: =(M5/M6) -> 70.642542 | N7: =(N5/N6) -> 82.171012 | O7: =(O5/O6) -> 93.260011 | P7: =(P5/P6) -> 106.4612 | Q7: =(Q5/Q6) -> 120.60058 | ... AO7: =(AO5/AO6) -> 764.34757
A8: customers_end | B8: Customers at end of quarter | C8: Customers | D8: series<quantity> | E8: customers | F8: retention_factor * cumulative(new_customers_scaled, opening_customers) | G8: Calculations!J8:AO8 | H8: Solves end = start * (1 - churn) + new without a feedback loop: new customers are not churned in the quarter they join. | J8: =(J6*(opening_customers+SUM($J7:J7))) -> 424 | K8: =(K6*(opening_customers+SUM($J7:K7))) -> 454.04 | L8: =(L6*(opening_customers+SUM($J7:L7))) -> 488.8784 | M8: =(M6*(opening_customers+SUM($J7:M7))) -> 529.32326 | N8: =(N6*(opening_customers+SUM($J7:N7))) -> 575.15033 | O8: =(O6*(opening_customers+SUM($J7:O7))) -> 625.14432 | P8: =(P6*(opening_customers+SUM($J7:P7))) -> 680.13855 | Q8: =(Q6*(opening_customers+SUM($J7:Q7))) -> 739.93301 | ... AO8: =(AO6*(opening_customers+SUM($J7:AO7))) -> 2869.2205
A9: customers_start | B9: Customers at start of quarter | C9: Customers | D9: series<quantity> | E9: customers | F9: if(flag(1, 1), opening_customers, lag(customers_end, 1)) | G9: Calculations!J9:AO9 | J9: =IF(AND(Timeline!J$9>=1,Timeline!J$9<=1),opening_customers,IF(Timeline!J$9>1,INDEX($J8:$AO8,1,Timeline!J$9-1),0)) -> 400 | K9: =IF(AND(Timeline!K$9>=1,Timeline!K$9<=1),opening_customers,IF(Timeline!K$9>1,INDEX($J8:$AO8,1,Timeline!K$9-1),0)) -> 424 | L9: =IF(AND(Timeline!L$9>=1,Timeline!L$9<=1),opening_customers,IF(Timeline!L$9>1,INDEX($J8:$AO8,1,Timeline!L$9-1),0)) -> 454.04 | M9: =IF(AND(Timeline!M$9>=1,Timeline!M$9<=1),opening_customers,IF(Timeline!M$9>1,INDEX($J8:$AO8,1,Timeline!M$9-1),0)) -> 488.8784 | N9: =IF(AND(Timeline!N$9>=1,Timeline!N$9<=1),opening_customers,IF(Timeline!N$9>1,INDEX($J8:$AO8,1,Timeline!N$9-1),0)) -> 529.32326 | O9: =IF(AND(Timeline!O$9>=1,Timeline!O$9<=1),opening_customers,IF(Timeline!O$9>1,INDEX($J8:$AO8,1,Timeline!O$9-1),0)) -> 575.15033 | P9: =IF(AND(Timeline!P$9>=1,Timeline!P$9<=1),opening_customers,IF(Timeline!P$9>1,INDEX($J8:$AO8,1,Timeline!P$9-1),0)) -> 625.14432 | Q9: =IF(AND(Timeline!Q$9>=1,Timeline!Q$9<=1),opening_customers,IF(Timeline!Q$9>1,INDEX($J8:$AO8,1,Timeline!Q$9-1),0)) -> 680.13855 | ... AO9: =IF(AND(Timeline!AO$9>=1,Timeline!AO$9<=1),opening_customers,IF(Timeline!AO$9>1,INDEX($J8:$AO8,1,Timeline!AO$9-1),0)) -> 2773.1463
A10: churned_customers | B10: Customers lost | C10: Customers | D10: series<quantity> | E10: customers | F10: customers_start * churn_rate_q | G10: Calculations!J10:AO10 | J10: =(J9*churn_rate_q) -> 16 | K10: =(K9*churn_rate_q) -> 16.96 | L10: =(L9*churn_rate_q) -> 18.1616 | M10: =(M9*churn_rate_q) -> 19.555136 | N10: =(N9*churn_rate_q) -> 21.172931 | O10: =(O9*churn_rate_q) -> 23.006013 | P10: =(P9*churn_rate_q) -> 25.005773 | Q10: =(Q9*churn_rate_q) -> 27.205542 | ... AO10: =(AO9*churn_rate_q) -> 110.92585
A11: net_new_customers | B11: Net new customers | C11: Customers | D11: series<quantity> | E11: customers | F11: new_customers - churned_customers | G11: Calculations!J11:AO11 | J11: =(J5-J10) -> 24 | K11: =(K5-K10) -> 30.04 | L11: =(L5-L10) -> 34.8384 | M11: =(M5-M10) -> 40.444864 | N11: =(N5-N10) -> 45.827069 | O11: =(O5-O10) -> 49.993987 | P11: =(P5-P10) -> 54.994227 | Q11: =(Q5-Q10) -> 59.794458 | ... AO11: =(AO5-AO10) -> 96.074147
A12: average_customers | B12: Average customers | C12: Customers | D12: series<quantity> | E12: customers | F12: (customers_start + customers_end) / 2 | G12: Calculations!J12:AO12 | J12: =((J9+J8)/2) -> 412 | K12: =((K9+K8)/2) -> 439.02 | L12: =((L9+L8)/2) -> 471.4592 | M12: =((M9+M8)/2) -> 509.10083 | N12: =((N9+N8)/2) -> 552.2368 | O12: =((O9+O8)/2) -> 600.14733 | P12: =((P9+P8)/2) -> 652.64143 | Q12: =((Q9+Q8)/2) -> 710.03578 | ... AO12: =((AO9+AO8)/2) -> 2821.1834
A13: price_growth_q | B13: Price increase per quarter | C13: Pricing | D13: percent | E13: fraction | F13: pow(1 + price_growth_annual, 0.25) - 1 | G13: Calculations!I13 | I13: =(POWER((1+price_growth_annual),0.25)-1) -> 0.0074170718
A14: price_index | B14: Price index | C14: Pricing | D14: series<float> | E14: index | F14: growth(1, price_growth_q) | G14: Calculations!J14:AO14 | H14: 1.0 in period 1. | J14: =(1)*(1+price_growth_q)^(Timeline!J$9-1) -> 1 | K14: =(1)*(1+price_growth_q)^(Timeline!K$9-1) -> 1.0074171 | L14: =(1)*(1+price_growth_q)^(Timeline!L$9-1) -> 1.0148892 | M14: =(1)*(1+price_growth_q)^(Timeline!M$9-1) -> 1.0224167 | N14: =(1)*(1+price_growth_q)^(Timeline!N$9-1) -> 1.03 | O14: =(1)*(1+price_growth_q)^(Timeline!O$9-1) -> 1.0376396 | P14: =(1)*(1+price_growth_q)^(Timeline!P$9-1) -> 1.0453358 | Q14: =(1)*(1+price_growth_q)^(Timeline!Q$9-1) -> 1.0530892 | ... AO14: =(1)*(1+price_growth_q)^(Timeline!AO$9-1) -> 1.2574435
A15: arpa_effective | B15: Average revenue per account (monthly, current price) | C15: Pricing | D15: series<currency> | E15: USD/customer | F15: arpa_monthly * price_index | G15: Calculations!J15:AO15 | J15: =(arpa_monthly*J14) -> 2000 | K15: =(arpa_monthly*K14) -> 2014.8341 | L15: =(arpa_monthly*L14) -> 2029.7783 | M15: =(arpa_monthly*M14) -> 2044.8333 | N15: =(arpa_monthly*N14) -> 2060 | O15: =(arpa_monthly*O14) -> 2075.2792 | P15: =(arpa_monthly*P14) -> 2090.6717 | Q15: =(arpa_monthly*Q14) -> 2106.1783 | ... AO15: =(arpa_monthly*AO14) -> 2514.8871
A16: mrr | B16: Monthly recurring revenue (end of quarter) | C16: Revenue | D16: series<currency> | E16: USD | F16: customers_end * arpa_effective | G16: Calculations!J16:AO16 | J16: =(J8*J15) -> 848000 | K16: =(K8*K15) -> 914815.29 | L16: =(L8*L15) -> 992314.77 | M16: =(M8*M15) -> 1082377.8 | N16: =(N8*N15) -> 1184809.7 | O16: =(O8*O15) -> 1297349 | P16: =(P8*P15) -> 1421946.4 | Q16: =(Q8*Q15) -> 1558430.9 | ... AO16: =(AO8*AO15) -> 7215765.4
A17: arr | B17: Annual recurring revenue | C17: Revenue | D17: series<currency> | E17: USD | F17: mrr * months_per_year | G17: Calculations!J17:AO17 | J17: =(J16*months_per_year) -> 10176000 | K17: =(K16*months_per_year) -> 10977784 | L17: =(L16*months_per_year) -> 11907777 | M17: =(M16*months_per_year) -> 12988534 | N17: =(N16*months_per_year) -> 14217716 | O17: =(O16*months_per_year) -> 15568188 | P17: =(P16*months_per_year) -> 17063357 | Q17: =(Q16*months_per_year) -> 18701170 | ... AO17: =(AO16*months_per_year) -> 86589185
A18: revenue | B18: Revenue | C18: Revenue | D18: series<currency> | E18: USD | F18: average_customers * arpa_effective * months_per_quarter | G18: Calculations!J18:AO18 | H18: Average customers over the quarter, three months each. | J18: =((J12*J15)*months_per_quarter) -> 2472000 | K18: =((K12*K15)*months_per_quarter) -> 2653657.5 | L18: =((L12*L15)*months_per_quarter) -> 2870873 | M18: =((M12*M15)*months_per_quarter) -> 3123079 | N18: =((N12*N15)*months_per_quarter) -> 3412823.4 | O18: =((O12*O15)*months_per_quarter) -> 3736419.7 | P18: =((P12*P15)*months_per_quarter) -> 4093376.9 | Q18: =((Q12*Q15)*months_per_quarter) -> 4486385.9 | ... AO18: =((AO12*AO15)*months_per_quarter) -> 21284873
A19: cogs_hosting | B19: Cost of revenue: hosting | C19: Cost of revenue | D19: series<currency> | E19: USD | F19: average_customers * hosting_cost_monthly * months_per_quarter | G19: Calculations!J19:AO19 | J19: =((J12*hosting_cost_monthly)*months_per_quarter) -> 173040 | K19: =((K12*hosting_cost_monthly)*months_per_quarter) -> 184388.4 | L19: =((L12*hosting_cost_monthly)*months_per_quarter) -> 198012.86 | M19: =((M12*hosting_cost_monthly)*months_per_quarter) -> 213822.35 | N19: =((N12*hosting_cost_monthly)*months_per_quarter) -> 231939.46 | O19: =((O12*hosting_cost_monthly)*months_per_quarter) -> 252061.88 | P19: =((P12*hosting_cost_monthly)*months_per_quarter) -> 274109.4 | Q19: =((Q12*hosting_cost_monthly)*months_per_quarter) -> 298215.03 | ... AO19: =((AO12*hosting_cost_monthly)*months_per_quarter) -> 1184897
A20: cogs_support | B20: Cost of revenue: support | C20: Cost of revenue | D20: series<currency> | E20: USD | F20: revenue * support_cost_pct | G20: Calculations!J20:AO20 | J20: =(J18*support_cost_pct) -> 148320 | K20: =(K18*support_cost_pct) -> 159219.45 | L20: =(L18*support_cost_pct) -> 172252.38 | M20: =(M18*support_cost_pct) -> 187384.74 | N20: =(N18*support_cost_pct) -> 204769.4 | O20: =(O18*support_cost_pct) -> 224185.18 | P20: =(P18*support_cost_pct) -> 245602.61 | Q20: =(Q18*support_cost_pct) -> 269183.15 | ... AO20: =(AO18*support_cost_pct) -> 1277092.4
A21: cogs_payments | B21: Cost of revenue: payment fees | C21: Cost of revenue | D21: series<currency> | E21: USD | F21: revenue * payment_fees_pct | G21: Calculations!J21:AO21 | J21: =(J18*payment_fees_pct) -> 61800 | K21: =(K18*payment_fees_pct) -> 66341.436 | L21: =(L18*payment_fees_pct) -> 71771.824 | M21: =(M18*payment_fees_pct) -> 78076.976 | N21: =(N18*payment_fees_pct) -> 85320.585 | O21: =(O18*payment_fees_pct) -> 93410.493 | P21: =(P18*payment_fees_pct) -> 102334.42 | Q21: =(Q18*payment_fees_pct) -> 112159.65 | ... AO21: =(AO18*payment_fees_pct) -> 532121.82
A22: cogs_total | B22: Cost of revenue | C22: Cost of revenue | D22: series<currency> | E22: USD | F22: sum(cogs_hosting, cogs_support, cogs_payments) | G22: Calculations!J22:AO22 | J22: =SUM(J19,J20,J21) -> 383160 | K22: =SUM(K19,K20,K21) -> 409949.28 | L22: =SUM(L19,L20,L21) -> 442037.07 | M22: =SUM(M19,M20,M21) -> 479284.07 | N22: =SUM(N19,N20,N21) -> 522029.45 | O22: =SUM(O19,O20,O21) -> 569657.55 | P22: =SUM(P19,P20,P21) -> 622046.43 | Q22: =SUM(Q19,Q20,Q21) -> 679557.83 | ... AO22: =SUM(AO19,AO20,AO21) -> 2994111.2
A23: gross_profit | B23: Gross profit | C23: Cost of revenue | D23: series<currency> | E23: USD | F23: revenue - cogs_total | G23: Calculations!J23:AO23 | J23: =(J18-J22) -> 2088840 | K23: =(K18-K22) -> 2243708.2 | L23: =(L18-L22) -> 2428835.9 | M23: =(M18-M22) -> 2643795 | N23: =(N18-N22) -> 2890794 | O23: =(O18-O22) -> 3166762.2 | P23: =(P18-P22) -> 3471330.4 | Q23: =(Q18-Q22) -> 3806828.1 | ... AO23: =(AO18-AO22) -> 18290762
A24: gross_margin | B24: Gross margin | C24: Cost of revenue | D24: series<percent> | E24: fraction | F24: gross_profit / revenue | G24: Calculations!J24:AO24 | H24: Revenue is positive in every period, so no zero guard is needed. | J24: =(J23/J18) -> 0.845 | K24: =(K23/K18) -> 0.84551537 | L24: =(L23/L18) -> 0.84602695 | M24: =(M23/M18) -> 0.84653476 | N24: =(N23/N18) -> 0.84703883 | O24: =(O23/O18) -> 0.8475392 | P24: =(P23/P18) -> 0.84803587 | Q24: =(Q23/Q18) -> 0.8485289 | ... AO24: =(AO23/AO18) -> 0.8593315
A25: sales_team_cost | B25: Sales team cost | C25: Operating expenses | D25: series<currency> | E25: USD | F25: sales_reps * sales_rep_cost_q | G25: Calculations!J25:AO25 | J25: =(Driver_Series!J4*sales_rep_cost_q) -> 270000 | K25: =(Driver_Series!K4*sales_rep_cost_q) -> 270000 | L25: =(Driver_Series!L4*sales_rep_cost_q) -> 315000 | M25: =(Driver_Series!M4*sales_rep_cost_q) -> 360000 | N25: =(Driver_Series!N4*sales_rep_cost_q) -> 405000 | O25: =(Driver_Series!O4*sales_rep_cost_q) -> 450000 | P25: =(Driver_Series!P4*sales_rep_cost_q) -> 495000 | Q25: =(Driver_Series!Q4*sales_rep_cost_q) -> 540000 | ... AO25: =(Driver_Series!AO4*sales_rep_cost_q) -> 1260000
A26: sales_marketing | B26: Sales and marketing | C26: Operating expenses | D26: series<currency> | E26: USD | F26: marketing_spend + sales_team_cost | G26: Calculations!J26:AO26 | J26: =(Driver_Series!J3+J25) -> 870000 | K26: =(Driver_Series!K3+K25) -> 970000 | L26: =(Driver_Series!L3+L25) -> 1115000 | M26: =(Driver_Series!M3+M25) -> 1260000 | N26: =(Driver_Series!N3+N25) -> 1405000 | O26: =(Driver_Series!O3+O25) -> 1550000 | P26: =(Driver_Series!P3+P25) -> 1695000 | Q26: =(Driver_Series!Q3+Q25) -> 1840000 | ... AO26: =(Driver_Series!AO3+AO25) -> 4360000
A27: research_development | B27: Research and development | C27: Operating expenses | D27: series<currency> | E27: USD | F27: engineers * engineer_cost_q | G27: Calculations!J27:AO27 | J27: =(Driver_Series!J5*engineer_cost_q) -> 1100000 | K27: =(Driver_Series!K5*engineer_cost_q) -> 1155000 | L27: =(Driver_Series!L5*engineer_cost_q) -> 1210000 | M27: =(Driver_Series!M5*engineer_cost_q) -> 1320000 | N27: =(Driver_Series!N5*engineer_cost_q) -> 1430000 | O27: =(Driver_Series!O5*engineer_cost_q) -> 1540000 | P27: =(Driver_Series!P5*engineer_cost_q) -> 1650000 | Q27: =(Driver_Series!Q5*engineer_cost_q) -> 1760000 | ... AO27: =(Driver_Series!AO5*engineer_cost_q) -> 3300000
A28: other_opex | B28: Other operating costs | C28: Operating expenses | D28: series<currency> | E28: USD | F28: growth(other_opex_initial_q, other_opex_growth_q) | G28: Calculations!J28:AO28 | J28: =(other_opex_initial_q)*(1+other_opex_growth_q)^(Timeline!J$9-1) -> 600000 | K28: =(other_opex_initial_q)*(1+other_opex_growth_q)^(Timeline!K$9-1) -> 615000 | L28: =(other_opex_initial_q)*(1+other_opex_growth_q)^(Timeline!L$9-1) -> 630375 | M28: =(other_opex_initial_q)*(1+other_opex_growth_q)^(Timeline!M$9-1) -> 646134.38 | N28: =(other_opex_initial_q)*(1+other_opex_growth_q)^(Timeline!N$9-1) -> 662287.73 | O28: =(other_opex_initial_q)*(1+other_opex_growth_q)^(Timeline!O$9-1) -> 678844.93 | P28: =(other_opex_initial_q)*(1+other_opex_growth_q)^(Timeline!P$9-1) -> 695816.05 | Q28: =(other_opex_initial_q)*(1+other_opex_growth_q)^(Timeline!Q$9-1) -> 713211.45 | ... AO28: =(other_opex_initial_q)*(1+other_opex_growth_q)^(Timeline!AO$9-1) -> 1290004.1
A29: general_admin | B29: General and administrative | C29: Operating expenses | D29: series<currency> | E29: USD | F29: ga_headcount * ga_cost_per_fte_q + other_opex | G29: Calculations!J29:AO29 | J29: =((Driver_Series!J6*ga_cost_per_fte_q)+J28) -> 840000 | K29: =((Driver_Series!K6*ga_cost_per_fte_q)+K28) -> 855000 | L29: =((Driver_Series!L6*ga_cost_per_fte_q)+L28) -> 870375 | M29: =((Driver_Series!M6*ga_cost_per_fte_q)+M28) -> 886134.38 | N29: =((Driver_Series!N6*ga_cost_per_fte_q)+N28) -> 982287.73 | O29: =((Driver_Series!O6*ga_cost_per_fte_q)+O28) -> 998844.93 | P29: =((Driver_Series!P6*ga_cost_per_fte_q)+P28) -> 1015816.1 | Q29: =((Driver_Series!Q6*ga_cost_per_fte_q)+Q28) -> 1033211.5 | ... AO29: =((Driver_Series!AO6*ga_cost_per_fte_q)+AO28) -> 1970004.1
A30: platform_rebuild | B30: Platform rebuild | C30: Operating expenses | D30: series<currency> | E30: USD | F30: spread(platform_rebuild_cost, platform_rebuild_start, platform_rebuild_periods) | G30: Calculations!J30:AO30 | J30: =IF(AND(Timeline!J$9>=platform_rebuild_start,Timeline!J$9<platform_rebuild_start+platform_rebuild_periods),platform_rebuild_cost/platform_rebuild_periods,0) -> 0 | K30: =IF(AND(Timeline!K$9>=platform_rebuild_start,Timeline!K$9<platform_rebuild_start+platform_rebuild_periods),platform_rebuild_cost/platform_rebuild_periods,0) -> 0 | L30: =IF(AND(Timeline!L$9>=platform_rebuild_start,Timeline!L$9<platform_rebuild_start+platform_rebuild_periods),platform_rebuild_cost/platform_rebuild_periods,0) -> 0 | M30: =IF(AND(Timeline!M$9>=platform_rebuild_start,Timeline!M$9<platform_rebuild_start+platform_rebuild_periods),platform_rebuild_cost/platform_rebuild_periods,0) -> 0 | N30: =IF(AND(Timeline!N$9>=platform_rebuild_start,Timeline!N$9<platform_rebuild_start+platform_rebuild_periods),platform_rebuild_cost/platform_rebuild_periods,0) -> 0 | O30: =IF(AND(Timeline!O$9>=platform_rebuild_start,Timeline!O$9<platform_rebuild_start+platform_rebuild_periods),platform_rebuild_cost/platform_rebuild_periods,0) -> 0 | P30: =IF(AND(Timeline!P$9>=platform_rebuild_start,Timeline!P$9<platform_rebuild_start+platform_rebuild_periods),platform_rebuild_cost/platform_rebuild_periods,0) -> 0 | Q30: =IF(AND(Timeline!Q$9>=platform_rebuild_start,Timeline!Q$9<platform_rebuild_start+platform_rebuild_periods),platform_rebuild_cost/platform_rebuild_periods,0) -> 0 | ... AO30: =IF(AND(Timeline!AO$9>=platform_rebuild_start,Timeline!AO$9<platform_rebuild_start+platform_rebuild_periods),platform_rebuild_cost/platform_rebuild_periods,0) -> 0
A31: opex_total | B31: Operating expenses | C31: Operating expenses | D31: series<currency> | E31: USD | F31: sum(sales_marketing, research_development, general_admin, platform_rebuild) | G31: Calculations!J31:AO31 | J31: =SUM(J26,J27,J29,J30) -> 2810000 | K31: =SUM(K26,K27,K29,K30) -> 2980000 | L31: =SUM(L26,L27,L29,L30) -> 3195375 | M31: =SUM(M26,M27,M29,M30) -> 3466134.4 | N31: =SUM(N26,N27,N29,N30) -> 3817287.7 | O31: =SUM(O26,O27,O29,O30) -> 4088844.9 | P31: =SUM(P26,P27,P29,P30) -> 4360816.1 | Q31: =SUM(Q26,Q27,Q29,Q30) -> 4633211.5 | ... AO31: =SUM(AO26,AO27,AO29,AO30) -> 9630004.1
A32: ebitda | B32: EBITDA | C32: Operating expenses | D32: series<currency> | E32: USD | F32: gross_profit - opex_total | G32: Calculations!J32:AO32 | J32: =(J23-J31) -> -721160 | K32: =(K23-K31) -> -736291.83 | L32: =(L23-L31) -> -766539.09 | M32: =(M23-M31) -> -822339.4 | N32: =(N23-N31) -> -926493.76 | O32: =(O23-O31) -> -922082.75 | P32: =(P23-P31) -> -889485.63 | Q32: =(Q23-Q31) -> -826383.39 | ... AO32: =(AO23-AO31) -> 8660757.6
A33: ebitda_margin | B33: EBITDA margin | C33: Operating expenses | D33: series<percent> | E33: fraction | F33: ebitda / revenue | G33: Calculations!J33:AO33 | J33: =(J32/J18) -> -0.29173139 | K33: =(K32/K18) -> -0.27746303 | L33: =(L32/L18) -> -0.26700557 | M33: =(M32/M18) -> -0.26331047 | N33: =(N32/N18) -> -0.27147428 | O33: =(O32/O18) -> -0.24678243 | P33: =(P32/P18) -> -0.21729874 | Q33: =(Q32/Q18) -> -0.18419802 | ... AO33: =(AO32/AO18) -> 0.40689731
A34: maintenance_capex | B34: Maintenance capex | C34: Capex | D34: series<currency> | E34: USD | F34: revenue * maintenance_capex_pct | G34: Calculations!J34:AO34 | J34: =(J18*maintenance_capex_pct) -> 37080 | K34: =(K18*maintenance_capex_pct) -> 39804.862 | L34: =(L18*maintenance_capex_pct) -> 43063.095 | M34: =(M18*maintenance_capex_pct) -> 46846.186 | N34: =(N18*maintenance_capex_pct) -> 51192.351 | O34: =(O18*maintenance_capex_pct) -> 56046.296 | P34: =(P18*maintenance_capex_pct) -> 61400.653 | Q34: =(Q18*maintenance_capex_pct) -> 67295.788 | ... AO34: =(AO18*maintenance_capex_pct) -> 319273.09
A35: capex_total | B35: Capex | C35: Capex | D35: series<currency> | E35: USD | F35: growth_capex + maintenance_capex | G35: Calculations!J35:AO35 | J35: =(Driver_Series!J7+J34) -> 437080 | K35: =(Driver_Series!K7+K34) -> 439804.86 | L35: =(Driver_Series!L7+L34) -> 443063.09 | M35: =(Driver_Series!M7+M34) -> 446846.19 | N35: =(Driver_Series!N7+N34) -> 301192.35 | O35: =(Driver_Series!O7+O34) -> 306046.3 | P35: =(Driver_Series!P7+P34) -> 311400.65 | Q35: =(Driver_Series!Q7+Q34) -> 317295.79 | ... AO35: =(Driver_Series!AO7+AO34) -> 619273.09
A36: depreciation | B36: Depreciation | C36: Capex | D36: series<currency> | E36: USD | F36: depreciation_sl(capex_total, asset_life_q) | G36: Calculations!J36:AO36 | H36: Each period's capex depreciated straight line from the period it is spent. | J36: =SUMPRODUCT((Timeline!$J$9:$AO$9<=Timeline!J$9)*(Timeline!$J$9:$AO$9>Timeline!J$9-asset_life_q),$J35:$AO35)/asset_life_q -> 36423.333 | K36: =SUMPRODUCT((Timeline!$J$9:$AO$9<=Timeline!K$9)*(Timeline!$J$9:$AO$9>Timeline!K$9-asset_life_q),$J35:$AO35)/asset_life_q -> 73073.738 | L36: =SUMPRODUCT((Timeline!$J$9:$AO$9<=Timeline!L$9)*(Timeline!$J$9:$AO$9>Timeline!L$9-asset_life_q),$J35:$AO35)/asset_life_q -> 109995.66 | M36: =SUMPRODUCT((Timeline!$J$9:$AO$9<=Timeline!M$9)*(Timeline!$J$9:$AO$9>Timeline!M$9-asset_life_q),$J35:$AO35)/asset_life_q -> 147232.85 | N36: =SUMPRODUCT((Timeline!$J$9:$AO$9<=Timeline!N$9)*(Timeline!$J$9:$AO$9>Timeline!N$9-asset_life_q),$J35:$AO35)/asset_life_q -> 172332.21 | O36: =SUMPRODUCT((Timeline!$J$9:$AO$9<=Timeline!O$9)*(Timeline!$J$9:$AO$9>Timeline!O$9-asset_life_q),$J35:$AO35)/asset_life_q -> 197836.07 | P36: =SUMPRODUCT((Timeline!$J$9:$AO$9<=Timeline!P$9)*(Timeline!$J$9:$AO$9>Timeline!P$9-asset_life_q),$J35:$AO35)/asset_life_q -> 223786.12 | Q36: =SUMPRODUCT((Timeline!$J$9:$AO$9<=Timeline!Q$9)*(Timeline!$J$9:$AO$9>Timeline!Q$9-asset_life_q),$J35:$AO35)/asset_life_q -> 250227.44 | ... AO36: =SUMPRODUCT((Timeline!$J$9:$AO$9<=Timeline!AO$9)*(Timeline!$J$9:$AO$9>Timeline!AO$9-asset_life_q),$J35:$AO35)/asset_life_q -> 550544.7
A37: ebit | B37: EBIT | C37: Capex | D37: series<currency> | E37: USD | F37: ebitda - depreciation | G37: Calculations!J37:AO37 | H37: No debt, so EBT equals EBIT. | J37: =(J32-J36) -> -757583.33 | K37: =(K32-K36) -> -809365.57 | L37: =(L32-L36) -> -876534.75 | M37: =(M32-M36) -> -969572.25 | N37: =(N32-N36) -> -1098826 | O37: =(O32-O36) -> -1119918.8 | P37: =(P32-P36) -> -1113271.8 | Q37: =(Q32-Q36) -> -1076610.8 | ... AO37: =(AO32-AO36) -> 8110212.9
A38: ebit_cumulative | B38: Cumulative EBIT | C38: Financing | D38: series<currency> | E38: USD | F38: cumulative(ebit, 0) | G38: Calculations!J38:AO38 | J38: =(0+SUM($J37:J37)) -> -757583.33 | K38: =(0+SUM($J37:K37)) -> -1566948.9 | L38: =(0+SUM($J37:L37)) -> -2443483.6 | M38: =(0+SUM($J37:M37)) -> -3413055.9 | N38: =(0+SUM($J37:N37)) -> -4511881.9 | O38: =(0+SUM($J37:O37)) -> -5631800.7 | P38: =(0+SUM($J37:P37)) -> -6745072.4 | Q38: =(0+SUM($J37:Q37)) -> -7821683.3 | ... AO38: =(0+SUM($J37:AO37)) -> 46432785
A39: taxable_income_cumulative | B39: Cumulative taxable income after losses | C39: Financing | D39: series<currency> | E39: USD | F39: max(0, running_max(ebit_cumulative)) | G39: Calculations!J39:AO39 | J39: =MAX(0,MAX($J38:J38)) -> 0 | K39: =MAX(0,MAX($J38:K38)) -> 0 | L39: =MAX(0,MAX($J38:L38)) -> 0 | M39: =MAX(0,MAX($J38:M38)) -> 0 | N39: =MAX(0,MAX($J38:N38)) -> 0 | O39: =MAX(0,MAX($J38:O38)) -> 0 | P39: =MAX(0,MAX($J38:P38)) -> 0 | Q39: =MAX(0,MAX($J38:Q38)) -> 0 | ... AO39: =MAX(0,MAX($J38:AO38)) -> 46432785
A40: taxable_income | B40: Taxable income | C40: Financing | D40: series<currency> | E40: USD | F40: taxable_income_cumulative - lag(taxable_income_cumulative, 1) | G40: Calculations!J40:AO40 | J40: =(J39-IF(Timeline!J$9>1,INDEX($J39:$AO39,1,Timeline!J$9-1),0)) -> 0 | K40: =(K39-IF(Timeline!K$9>1,INDEX($J39:$AO39,1,Timeline!K$9-1),0)) -> 0 | L40: =(L39-IF(Timeline!L$9>1,INDEX($J39:$AO39,1,Timeline!L$9-1),0)) -> 0 | M40: =(M39-IF(Timeline!M$9>1,INDEX($J39:$AO39,1,Timeline!M$9-1),0)) -> 0 | N40: =(N39-IF(Timeline!N$9>1,INDEX($J39:$AO39,1,Timeline!N$9-1),0)) -> 0 | O40: =(O39-IF(Timeline!O$9>1,INDEX($J39:$AO39,1,Timeline!O$9-1),0)) -> 0 | P40: =(P39-IF(Timeline!P$9>1,INDEX($J39:$AO39,1,Timeline!P$9-1),0)) -> 0 | Q40: =(Q39-IF(Timeline!Q$9>1,INDEX($J39:$AO39,1,Timeline!Q$9-1),0)) -> 0 | ... AO40: =(AO39-IF(Timeline!AO$9>1,INDEX($J39:$AO39,1,Timeline!AO$9-1),0)) -> 8110212.9
A41: tax | B41: Income tax | C41: Financing | D41: series<currency> | E41: USD | F41: taxable_income * tax_rate | G41: Calculations!J41:AO41 | H41: Paid in the period incurred. | J41: =(J40*tax_rate) -> 0 | K41: =(K40*tax_rate) -> 0 | L41: =(L40*tax_rate) -> 0 | M41: =(M40*tax_rate) -> 0 | N41: =(N40*tax_rate) -> 0 | O41: =(O40*tax_rate) -> 0 | P41: =(P40*tax_rate) -> 0 | Q41: =(Q40*tax_rate) -> 0 | ... AO41: =(AO40*tax_rate) -> 2027553.2
A42: net_income | B42: Net income | C42: Financing | D42: series<currency> | E42: USD | F42: ebit - tax | G42: Calculations!J42:AO42 | J42: =(J37-J41) -> -757583.33 | K42: =(K37-K41) -> -809365.57 | L42: =(L37-L41) -> -876534.75 | M42: =(M37-M41) -> -969572.25 | N42: =(N37-N41) -> -1098826 | O42: =(O37-O41) -> -1119918.8 | P42: =(P37-P41) -> -1113271.8 | Q42: =(Q37-Q41) -> -1076610.8 | ... AO42: =(AO37-AO41) -> 6082659.7
A43: accounts_receivable | B43: Accounts receivable | C43: Financing | D43: series<currency> | E43: USD | F43: revenue * ar_days / days_per_quarter | G43: Calculations!J43:AO43 | H43: End-of-period balance. | J43: =((J18*ar_days)/days_per_quarter) -> 1219068.5 | K43: =((K18*ar_days)/days_per_quarter) -> 1308653 | L43: =((L18*ar_days)/days_per_quarter) -> 1415773 | M43: =((M18*ar_days)/days_per_quarter) -> 1540148.6 | N43: =((N18*ar_days)/days_per_quarter) -> 1683036.2 | O43: =((O18*ar_days)/days_per_quarter) -> 1842618 | P43: =((P18*ar_days)/days_per_quarter) -> 2018651.6 | Q43: =((Q18*ar_days)/days_per_quarter) -> 2212464.3 | ... AO43: =((AO18*ar_days)/days_per_quarter) -> 10496650
A44: deferred_revenue | B44: Deferred revenue | C44: Financing | D44: series<currency> | E44: USD | F44: revenue * annual_prepay_share * prepaid_quarters | G44: Calculations!J44:AO44 | H44: Unearned annual prepayments at quarter end. | J44: =((J18*annual_prepay_share)*prepaid_quarters) -> 1483200 | K44: =((K18*annual_prepay_share)*prepaid_quarters) -> 1592194.5 | L44: =((L18*annual_prepay_share)*prepaid_quarters) -> 1722523.8 | M44: =((M18*annual_prepay_share)*prepaid_quarters) -> 1873847.4 | N44: =((N18*annual_prepay_share)*prepaid_quarters) -> 2047694 | O44: =((O18*annual_prepay_share)*prepaid_quarters) -> 2241851.8 | P44: =((P18*annual_prepay_share)*prepaid_quarters) -> 2456026.1 | Q44: =((Q18*annual_prepay_share)*prepaid_quarters) -> 2691831.5 | ... AO44: =((AO18*annual_prepay_share)*prepaid_quarters) -> 12770924
A45: accounts_payable | B45: Accounts payable | C45: Financing | D45: series<currency> | E45: USD | F45: (cogs_total + other_opex) * ap_days / days_per_quarter | G45: Calculations!J45:AO45 | H45: End-of-period balance. | J45: =(((J22+J28)*ap_days)/days_per_quarter) -> 323230.68 | K45: =(((K22+K28)*ap_days)/days_per_quarter) -> 336969.63 | L45: =(((L22+L28)*ap_days)/days_per_quarter) -> 352573.83 | M45: =(((M22+M28)*ap_days)/days_per_quarter) -> 370000.58 | N45: =(((N22+N28)*ap_days)/days_per_quarter) -> 389364.55 | O45: =(((O22+O28)*ap_days)/days_per_quarter) -> 410466.57 | P45: =(((P22+P28)*ap_days)/days_per_quarter) -> 433269.86 | Q45: =(((Q22+Q28)*ap_days)/days_per_quarter) -> 457896.75 | ... AO45: =(((AO22+AO28)*ap_days)/days_per_quarter) -> 1408476.3
A46: net_working_capital | B46: Net working capital | C46: Financing | D46: series<currency> | E46: USD | F46: accounts_receivable - deferred_revenue - accounts_payable | G46: Calculations!J46:AO46 | H46: Negative when prepayments exceed receivables. | J46: =((J43-J44)-J45) -> -587362.19 | K46: =((K43-K44)-K45) -> -620511.11 | L46: =((L43-L44)-L45) -> -659324.64 | M46: =((M43-M44)-M45) -> -703699.44 | N46: =((N43-N44)-N45) -> -754022.4 | O46: =((O43-O44)-O45) -> -809700.46 | P46: =((P43-P44)-P45) -> -870644.37 | Q46: =((Q43-Q44)-Q45) -> -937264.01 | ... AO46: =((AO43-AO44)-AO45) -> -3682750.3
A47: change_in_nwc | B47: Change in net working capital | C47: Financing | D47: series<currency> | E47: USD | F47: net_working_capital - lag(net_working_capital, 1) | G47: Calculations!J47:AO47 | H47: Opening working capital is zero. | J47: =(J46-IF(Timeline!J$9>1,INDEX($J46:$AO46,1,Timeline!J$9-1),0)) -> -587362.19 | K47: =(K46-IF(Timeline!K$9>1,INDEX($J46:$AO46,1,Timeline!K$9-1),0)) -> -33148.918 | L47: =(L46-IF(Timeline!L$9>1,INDEX($J46:$AO46,1,Timeline!L$9-1),0)) -> -38813.532 | M47: =(M46-IF(Timeline!M$9>1,INDEX($J46:$AO46,1,Timeline!M$9-1),0)) -> -44374.799 | N47: =(N46-IF(Timeline!N$9>1,INDEX($J46:$AO46,1,Timeline!N$9-1),0)) -> -50322.957 | O47: =(O46-IF(Timeline!O$9>1,INDEX($J46:$AO46,1,Timeline!O$9-1),0)) -> -55678.062 | P47: =(P46-IF(Timeline!P$9>1,INDEX($J46:$AO46,1,Timeline!P$9-1),0)) -> -60943.912 | Q47: =(Q46-IF(Timeline!Q$9>1,INDEX($J46:$AO46,1,Timeline!Q$9-1),0)) -> -66619.637 | ... AO47: =(AO46-IF(Timeline!AO$9>1,INDEX($J46:$AO46,1,Timeline!AO$9-1),0)) -> -141626
A48: free_cash_flow | B48: Free cash flow (unlevered) | C48: Financing | D48: series<currency> | E48: USD | F48: ebitda - tax - capex_total - change_in_nwc | G48: Calculations!J48:AO48 | J48: =(((J32-J41)-J35)-J47) -> -570877.81 | K48: =(((K32-K41)-K35)-K47) -> -1142947.8 | L48: =(((L32-L41)-L35)-L47) -> -1170788.7 | M48: =(((M32-M41)-M35)-M47) -> -1224810.8 | N48: =(((N32-N41)-N35)-N47) -> -1177363.2 | O48: =(((O32-O41)-O35)-O47) -> -1172451 | P48: =(((P32-P41)-P35)-P47) -> -1139942.4 | Q48: =(((Q32-Q41)-Q35)-Q47) -> -1077059.5 | ... AO48: =(((AO32-AO41)-AO35)-AO47) -> 6155557.3
A49: cumulative_fcf | B49: Cumulative free cash flow | C49: Financing | D49: series<currency> | E49: USD | F49: cumulative(free_cash_flow, 0) | G49: Calculations!J49:AO49 | J49: =(0+SUM($J48:J48)) -> -570877.81 | K49: =(0+SUM($J48:K48)) -> -1713825.6 | L49: =(0+SUM($J48:L48)) -> -2884614.2 | M49: =(0+SUM($J48:M48)) -> -4109425 | N49: =(0+SUM($J48:N48)) -> -5286788.2 | O49: =(0+SUM($J48:O48)) -> -6459239.2 | P49: =(0+SUM($J48:P48)) -> -7599181.5 | Q49: =(0+SUM($J48:Q48)) -> -8676241.1 | ... AO49: =(0+SUM($J48:AO48)) -> 35334195
A50: net_cash_flow | B50: Net cash flow | C50: Financing | D50: series<currency> | E50: USD | F50: free_cash_flow + equity_raises | G50: Calculations!J50:AO50 | H50: No interest on cash (that would be circular). | J50: =(J48+Driver_Series!J8) -> -570877.81 | K50: =(K48+Driver_Series!K8) -> -1142947.8 | L50: =(L48+Driver_Series!L8) -> -1170788.7 | M50: =(M48+Driver_Series!M8) -> -1224810.8 | N50: =(N48+Driver_Series!N8) -> -1177363.2 | O50: =(O48+Driver_Series!O8) -> 28827549 | P50: =(P48+Driver_Series!P8) -> -1139942.4 | Q50: =(Q48+Driver_Series!Q8) -> -1077059.5 | ... AO50: =(AO48+Driver_Series!AO8) -> 6155557.3
A51: cash_balance | B51: Cash balance | C51: Financing | D51: series<currency> | E51: USD | F51: cumulative(net_cash_flow, opening_cash) | G51: Calculations!J51:AO51 | H51: End of period. | J51: =(opening_cash+SUM($J50:J50)) -> 24429122 | K51: =(opening_cash+SUM($J50:K50)) -> 23286174 | L51: =(opening_cash+SUM($J50:L50)) -> 22115386 | M51: =(opening_cash+SUM($J50:M50)) -> 20890575 | N51: =(opening_cash+SUM($J50:N50)) -> 19713212 | O51: =(opening_cash+SUM($J50:O50)) -> 48540761 | P51: =(opening_cash+SUM($J50:P50)) -> 47400818 | Q51: =(opening_cash+SUM($J50:Q50)) -> 46323759 | ... AO51: =(opening_cash+SUM($J50:AO50)) -> 1.3033419e+08
A52: cash_above_minimum | B52: Cash above minimum | C52: Financing | D52: series<bool> | E52: flag | F52: cash_balance >= min_cash_balance | G52: Calculations!J52:AO52 | H52: Check. | J52: =(J51>=min_cash_balance) -> TRUE | K52: =(K51>=min_cash_balance) -> TRUE | L52: =(L51>=min_cash_balance) -> TRUE | M52: =(M51>=min_cash_balance) -> TRUE | N52: =(N51>=min_cash_balance) -> TRUE | O52: =(O51>=min_cash_balance) -> TRUE | P52: =(P51>=min_cash_balance) -> TRUE | Q52: =(Q51>=min_cash_balance) -> TRUE | ... AO52: =(AO51>=min_cash_balance) -> TRUE
A53: cash_burn | B53: Cash burn | C53: Financing | D53: series<currency> | E53: USD | F53: max(0, 0 - free_cash_flow) | G53: Calculations!J53:AO53 | H53: Zero once free cash flow is positive. | J53: =MAX(0,(0-J48)) -> 570877.81 | K53: =MAX(0,(0-K48)) -> 1142947.8 | L53: =MAX(0,(0-L48)) -> 1170788.7 | M53: =MAX(0,(0-M48)) -> 1224810.8 | N53: =MAX(0,(0-N48)) -> 1177363.2 | O53: =MAX(0,(0-O48)) -> 1172451 | P53: =MAX(0,(0-P48)) -> 1139942.4 | Q53: =MAX(0,(0-Q48)) -> 1077059.5 | ... AO53: =MAX(0,(0-AO48)) -> 0
A54: runway_quarters | B54: Runway at current burn | C54: Financing | D54: series<float> | E54: quarters | F54: safe_divide(cash_balance, cash_burn, 0) | G54: Calculations!J54:AO54 | H54: 0 when the company isn't burning cash. | J54: =IF((J53)=0,0,(J51)/(J53)) -> 42.792208 | K54: =IF((K53)=0,0,(K51)/(K53)) -> 20.373787 | L54: =IF((L53)=0,0,(L51)/(L53)) -> 18.889307 | M54: =IF((M53)=0,0,(M51)/(M53)) -> 17.056165 | N54: =IF((N53)=0,0,(N51)/(N53)) -> 16.743527 | O54: =IF((O53)=0,0,(O51)/(O53)) -> 41.4011 | P54: =IF((P53)=0,0,(P51)/(P53)) -> 41.581767 | Q54: =IF((Q53)=0,0,(Q51)/(Q53)) -> 43.009469 | ... AO54: =IF((AO53)=0,0,(AO51)/(AO53)) -> 0
A55: cac_fully_loaded | B55: Customer acquisition cost (fully loaded) | C55: Unit economics | D55: series<currency> | E55: USD/customer | F55: safe_divide(sales_marketing, new_customers, 0) | G55: Calculations!J55:AO55 | H55: Sales and marketing per new customer. | J55: =IF((J5)=0,0,(J26)/(J5)) -> 21750 | K55: =IF((K5)=0,0,(K26)/(K5)) -> 20638.298 | L55: =IF((L5)=0,0,(L26)/(L5)) -> 21037.736 | M55: =IF((M5)=0,0,(M26)/(M5)) -> 21000 | N55: =IF((N5)=0,0,(N26)/(N5)) -> 20970.149 | O55: =IF((O5)=0,0,(O26)/(O5)) -> 21232.877 | P55: =IF((P5)=0,0,(P26)/(P5)) -> 21187.5 | Q55: =IF((Q5)=0,0,(Q26)/(Q5)) -> 21149.425 | ... AO55: =IF((AO5)=0,0,(AO26)/(AO5)) -> 21062.802
A56: gross_profit_per_customer_month | B56: Gross profit per customer per month | C56: Unit economics | D56: series<currency> | E56: USD/customer | F56: arpa_effective * gross_margin | G56: Calculations!J56:AO56 | J56: =(J15*J24) -> 1690 | K56: =(K15*K24) -> 1703.5732 | L56: =(L15*L24) -> 1717.2472 | M56: =(M15*M24) -> 1731.0225 | N56: =(N15*N24) -> 1744.9 | O56: =(O15*O24) -> 1758.8804 | P56: =(P15*P24) -> 1772.9646 | Q56: =(Q15*Q24) -> 1787.1532 | ... AO56: =(AO15*AO24) -> 2161.1217
A57: customer_lifetime_quarters | B57: Expected customer lifetime | C57: Unit economics | D57: float | E57: quarters | F57: 1 / churn_rate_q | G57: Calculations!I57 | I57: =(1/churn_rate_q) -> 25
A58: lifetime_value | B58: Customer lifetime value | C58: Unit economics | D58: series<currency> | E58: USD/customer | F58: gross_profit_per_customer_month * months_per_quarter * customer_lifetime_quarters | G58: Calculations!J58:AO58 | H58: Gross profit over the expected lifetime. | J58: =((J56*months_per_quarter)*customer_lifetime_quarters) -> 126750 | K58: =((K56*months_per_quarter)*customer_lifetime_quarters) -> 127767.99 | L58: =((L56*months_per_quarter)*customer_lifetime_quarters) -> 128793.54 | M58: =((M56*months_per_quarter)*customer_lifetime_quarters) -> 129826.69 | N58: =((N56*months_per_quarter)*customer_lifetime_quarters) -> 130867.5 | O58: =((O56*months_per_quarter)*customer_lifetime_quarters) -> 131916.03 | P58: =((P56*months_per_quarter)*customer_lifetime_quarters) -> 132972.34 | Q58: =((Q56*months_per_quarter)*customer_lifetime_quarters) -> 134036.49 | ... AO58: =((AO56*months_per_quarter)*customer_lifetime_quarters) -> 162084.12
A59: ltv_to_cac | B59: Lifetime value to CAC | C59: Unit economics | D59: series<float> | E59: ratio | F59: safe_divide(lifetime_value, cac_fully_loaded, 0) | G59: Calculations!J59:AO59 | J59: =IF((J55)=0,0,(J58)/(J55)) -> 5.8275862 | K59: =IF((K55)=0,0,(K58)/(K55)) -> 6.1908203 | L59: =IF((L55)=0,0,(L58)/(L55)) -> 6.1220246 | M59: =IF((M55)=0,0,(M58)/(M55)) -> 6.1822232 | N59: =IF((N55)=0,0,(N58)/(N55)) -> 6.2406566 | O59: =IF((O55)=0,0,(O58)/(O55)) -> 6.2128196 | P59: =IF((P55)=0,0,(P58)/(P55)) -> 6.2759808 | Q59: =IF((Q55)=0,0,(Q58)/(Q55)) -> 6.3375948 | ... AO59: =IF((AO55)=0,0,(AO58)/(AO55)) -> 7.6952784
A60: cac_payback_months | B60: CAC payback | C60: Unit economics | D60: series<float> | E60: months | F60: safe_divide(cac_fully_loaded, gross_profit_per_customer_month, 0) | G60: Calculations!J60:AO60 | H60: Months of gross profit to recover acquisition cost. | J60: =IF((J56)=0,0,(J55)/(J56)) -> 12.869822 | K60: =IF((K56)=0,0,(K55)/(K56)) -> 12.114711 | L60: =IF((L56)=0,0,(L55)/(L56)) -> 12.250849 | M60: =IF((M56)=0,0,(M55)/(M56)) -> 12.131558 | N60: =IF((N56)=0,0,(N55)/(N56)) -> 12.017966 | O60: =IF((O56)=0,0,(O55)/(O56)) -> 12.071814 | P60: =IF((P56)=0,0,(P55)/(P56)) -> 11.950323 | Q60: =IF((Q56)=0,0,(Q55)/(Q56)) -> 11.834143 | ... AO60: =IF((AO56)=0,0,(AO55)/(AO56)) -> 9.7462361
A61: revenue_growth_yoy | B61: Revenue growth, year over year | C61: Unit economics | D61: series<percent> | E61: fraction | F61: safe_divide(revenue - lag(revenue, 4), lag(revenue, 4), 0) | G61: Calculations!J61:AO61 | H61: 0 in the first year, which has no prior-year quarter. | J61: =IF((IF(Timeline!J$9>4,INDEX($J18:$AO18,1,Timeline!J$9-4),0))=0,0,((J18-IF(Timeline!J$9>4,INDEX($J18:$AO18,1,Timeline!J$9-4),0)))/(IF(Timeline!J$9>4,INDEX($J18:$AO18,1,Timeline!J$9-4),0))) -> 0 | K61: =IF((IF(Timeline!K$9>4,INDEX($J18:$AO18,1,Timeline!K$9-4),0))=0,0,((K18-IF(Timeline!K$9>4,INDEX($J18:$AO18,1,Timeline!K$9-4),0)))/(IF(Timeline!K$9>4,INDEX($J18:$AO18,1,Timeline!K$9-4),0))) -> 0 | L61: =IF((IF(Timeline!L$9>4,INDEX($J18:$AO18,1,Timeline!L$9-4),0))=0,0,((L18-IF(Timeline!L$9>4,INDEX($J18:$AO18,1,Timeline!L$9-4),0)))/(IF(Timeline!L$9>4,INDEX($J18:$AO18,1,Timeline!L$9-4),0))) -> 0 | M61: =IF((IF(Timeline!M$9>4,INDEX($J18:$AO18,1,Timeline!M$9-4),0))=0,0,((M18-IF(Timeline!M$9>4,INDEX($J18:$AO18,1,Timeline!M$9-4),0)))/(IF(Timeline!M$9>4,INDEX($J18:$AO18,1,Timeline!M$9-4),0))) -> 0 | N61: =IF((IF(Timeline!N$9>4,INDEX($J18:$AO18,1,Timeline!N$9-4),0))=0,0,((N18-IF(Timeline!N$9>4,INDEX($J18:$AO18,1,Timeline!N$9-4),0)))/(IF(Timeline!N$9>4,INDEX($J18:$AO18,1,Timeline!N$9-4),0))) -> 0.380592 | O61: =IF((IF(Timeline!O$9>4,INDEX($J18:$AO18,1,Timeline!O$9-4),0))=0,0,((O18-IF(Timeline!O$9>4,INDEX($J18:$AO18,1,Timeline!O$9-4),0)))/(IF(Timeline!O$9>4,INDEX($J18:$AO18,1,Timeline!O$9-4),0))) -> 0.40802639 | P61: =IF((IF(Timeline!P$9>4,INDEX($J18:$AO18,1,Timeline!P$9-4),0))=0,0,((P18-IF(Timeline!P$9>4,INDEX($J18:$AO18,1,Timeline!P$9-4),0)))/(IF(Timeline!P$9>4,INDEX($J18:$AO18,1,Timeline!P$9-4),0))) -> 0.42583001 | Q61: =IF((IF(Timeline!Q$9>4,INDEX($J18:$AO18,1,Timeline!Q$9-4),0))=0,0,((Q18-IF(Timeline!Q$9>4,INDEX($J18:$AO18,1,Timeline!Q$9-4),0)))/(IF(Timeline!Q$9>4,INDEX($J18:$AO18,1,Timeline!Q$9-4),0))) -> 0.43652653 | ... AO61: =IF((IF(Timeline!AO$9>4,INDEX($J18:$AO18,1,Timeline!AO$9-4),0))=0,0,((AO18-IF(Timeline!AO$9>4,INDEX($J18:$AO18,1,Timeline!AO$9-4),0)))/(IF(Timeline!AO$9>4,INDEX($J18:$AO18,1,Timeline!AO$9-4),0))) -> 0.19176707
A62: rule_of_40 | B62: Rule of 40 score | C62: Unit economics | D62: series<percent> | E62: fraction | F62: revenue_growth_yoy + ebitda_margin | G62: Calculations!J62:AO62 | H62: Growth plus EBITDA margin; 40% or more is the usual bar. | J62: =(J61+J33) -> -0.29173139 | K62: =(K61+K33) -> -0.27746303 | L62: =(L61+L33) -> -0.26700557 | M62: =(M61+M33) -> -0.26331047 | N62: =(N61+N33) -> 0.10911772 | O62: =(O61+O33) -> 0.16124396 | P62: =(P61+P33) -> 0.20853127 | Q62: =(Q61+Q33) -> 0.25232851 | ... AO62: =(AO61+AO33) -> 0.59866438
A63: rule_of_40_met | B63: Rule of 40 met | C63: Unit economics | D63: series<bool> | E63: flag | F63: rule_of_40 >= 0.4 | G63: Calculations!J63:AO63 | H63: Check. | J63: =(J62>=0.4) -> FALSE | K63: =(K62>=0.4) -> FALSE | L63: =(L62>=0.4) -> FALSE | M63: =(M62>=0.4) -> FALSE | N63: =(N62>=0.4) -> FALSE | O63: =(O62>=0.4) -> FALSE | P63: =(P62>=0.4) -> FALSE | Q63: =(Q62>=0.4) -> FALSE | ... AO63: =(AO62>=0.4) -> TRUE
A64: net_new_arr | B64: Net new ARR | C64: Unit economics | D64: series<currency> | E64: USD | F64: arr - lag(arr, 1) | G64: Calculations!J64:AO64 | H64: Period 1 counts all opening ARR. | J64: =(J17-IF(Timeline!J$9>1,INDEX($J17:$AO17,1,Timeline!J$9-1),0)) -> 10176000 | K64: =(K17-IF(Timeline!K$9>1,INDEX($J17:$AO17,1,Timeline!K$9-1),0)) -> 801783.53 | L64: =(L17-IF(Timeline!L$9>1,INDEX($J17:$AO17,1,Timeline!L$9-1),0)) -> 929993.75 | M64: =(M17-IF(Timeline!M$9>1,INDEX($J17:$AO17,1,Timeline!M$9-1),0)) -> 1080756.9 | N64: =(N17-IF(Timeline!N$9>1,INDEX($J17:$AO17,1,Timeline!N$9-1),0)) -> 1229182 | O64: =(O17-IF(Timeline!O$9>1,INDEX($J17:$AO17,1,Timeline!O$9-1),0)) -> 1350471.6 | P64: =(P17-IF(Timeline!P$9>1,INDEX($J17:$AO17,1,Timeline!P$9-1),0)) -> 1495168.8 | Q64: =(Q17-IF(Timeline!Q$9>1,INDEX($J17:$AO17,1,Timeline!Q$9-1),0)) -> 1637813.6 | ... AO64: =(AO17-IF(Timeline!AO$9>1,INDEX($J17:$AO17,1,Timeline!AO$9-1),0)) -> 3515550.7
A65: burn_multiple | B65: Burn multiple | C65: Unit economics | D65: series<float> | E65: ratio | F65: safe_divide(cash_burn, net_new_arr, 0) | G65: Calculations!J65:AO65 | H65: Cash burned per dollar of net new ARR; 0 once burn stops. | J65: =IF((J64)=0,0,(J53)/(J64)) -> 0.056100414 | K65: =IF((K64)=0,0,(K53)/(K64)) -> 1.4255067 | L65: =IF((L64)=0,0,(L53)/(L64)) -> 1.258921 | M65: =IF((M64)=0,0,(M53)/(M64)) -> 1.1332898 | N65: =IF((N64)=0,0,(N53)/(N64)) -> 0.95784279 | O65: =IF((O64)=0,0,(O53)/(O64)) -> 0.86817894 | P65: =IF((P64)=0,0,(P53)/(P64)) -> 0.76241716 | Q65: =IF((Q64)=0,0,(Q53)/(Q64)) -> 0.65762033 | ... AO65: =IF((AO64)=0,0,(AO53)/(AO64)) -> 0
A66: headcount | B66: Headcount | C66: Unit economics | D66: series<count> | E66: FTE | F66: sum(sales_reps, engineers, ga_headcount) | G66: Calculations!J66:AO66 | J66: =SUM(Driver_Series!J4,Driver_Series!J5,Driver_Series!J6) -> 32 | K66: =SUM(Driver_Series!K4,Driver_Series!K5,Driver_Series!K6) -> 33 | L66: =SUM(Driver_Series!L4,Driver_Series!L5,Driver_Series!L6) -> 35 | M66: =SUM(Driver_Series!M4,Driver_Series!M5,Driver_Series!M6) -> 38 | N66: =SUM(Driver_Series!N4,Driver_Series!N5,Driver_Series!N6) -> 43 | O66: =SUM(Driver_Series!O4,Driver_Series!O5,Driver_Series!O6) -> 46 | P66: =SUM(Driver_Series!P4,Driver_Series!P5,Driver_Series!P6) -> 49 | Q66: =SUM(Driver_Series!Q4,Driver_Series!Q5,Driver_Series!Q6) -> 52 | ... AO66: =SUM(Driver_Series!AO4,Driver_Series!AO5,Driver_Series!AO6) -> 105
A67: revenue_per_employee | B67: Annualized revenue per employee | C67: Unit economics | D67: series<currency> | E67: USD/FTE | F67: revenue * 4 / headcount | G67: Calculations!J67:AO67 | J67: =((J18*4)/J66) -> 309000 | K67: =((K18*4)/K66) -> 321655.45 | L67: =((L18*4)/L66) -> 328099.77 | M67: =((M18*4)/M66) -> 328745.16 | N67: =((N18*4)/N66) -> 317471.95 | O67: =((O18*4)/O66) -> 324906.06 | P67: =((P18*4)/P66) -> 334153.21 | Q67: =((Q18*4)/Q66) -> 345106.61 | ... AO67: =((AO18*4)/AO66) -> 810852.3
A68: customers_won_total | B68: Customers won, total | C68: Unit economics | D68: quantity | E68: customers | F68: total(new_customers) | G68: Calculations!I68 | I68: =SUM($J5:$AO5) -> 4272
A69: discount_rate_q | B69: Discount rate (quarterly) | C69: Valuation | D69: percent | E69: fraction | F69: pow(1 + discount_rate_annual, 0.25) - 1 | G69: Calculations!I69 | I69: =(POWER((1+discount_rate_annual),0.25)-1) -> 0.042246635
A70: terminal_growth_q | B70: Terminal growth (quarterly) | C70: Valuation | D70: percent | E70: fraction | F70: pow(1 + terminal_growth_annual, 0.25) - 1 | G70: Calculations!I70 | I70: =(POWER((1+terminal_growth_annual),0.25)-1) -> 0.0074170718
A71: terminal_flag | B71: Terminal period flag | C71: Valuation | D71: series<bool> | E71: flag | F71: flag(terminal_period, terminal_period) | G71: Calculations!J71:AO71 | J71: =AND(Timeline!J$9>=terminal_period,Timeline!J$9<=terminal_period) -> FALSE | K71: =AND(Timeline!K$9>=terminal_period,Timeline!K$9<=terminal_period) -> FALSE | L71: =AND(Timeline!L$9>=terminal_period,Timeline!L$9<=terminal_period) -> FALSE | M71: =AND(Timeline!M$9>=terminal_period,Timeline!M$9<=terminal_period) -> FALSE | N71: =AND(Timeline!N$9>=terminal_period,Timeline!N$9<=terminal_period) -> FALSE | O71: =AND(Timeline!O$9>=terminal_period,Timeline!O$9<=terminal_period) -> FALSE | P71: =AND(Timeline!P$9>=terminal_period,Timeline!P$9<=terminal_period) -> FALSE | Q71: =AND(Timeline!Q$9>=terminal_period,Timeline!Q$9<=terminal_period) -> FALSE | ... AO71: =AND(Timeline!AO$9>=terminal_period,Timeline!AO$9<=terminal_period) -> TRUE
A72: terminal_fcf_series | B72: FCF in terminal period | C72: Valuation | D72: series<currency> | E72: USD | F72: if(terminal_flag, free_cash_flow, 0) | G72: Calculations!J72:AO72 | J72: =IF(J71,J48,0) -> 0 | K72: =IF(K71,K48,0) -> 0 | L72: =IF(L71,L48,0) -> 0 | M72: =IF(M71,M48,0) -> 0 | N72: =IF(N71,N48,0) -> 0 | O72: =IF(O71,O48,0) -> 0 | P72: =IF(P71,P48,0) -> 0 | Q72: =IF(Q71,Q48,0) -> 0 | ... AO72: =IF(AO71,AO48,0) -> 6155557.3
A73: terminal_fcf | B73: Terminal-period FCF | C73: Valuation | D73: currency | E73: USD | F73: total(terminal_fcf_series) | G73: Calculations!I73 | I73: =SUM($J72:$AO72) -> 6155557.3
A74: terminal_value | B74: Terminal value (Gordon growth) | C74: Valuation | D74: currency | E74: USD | F74: terminal_fcf * (1 + terminal_growth_q) / (discount_rate_q - terminal_growth_q) | G74: Calculations!I74 | H74: Value at end of terminal period. | I74: =((terminal_fcf*(1+terminal_growth_q))/(discount_rate_q-terminal_growth_q)) -> 1.7804454e+08
A75: terminal_value_flow | B75: Terminal value in cash flow | C75: Valuation | D75: series<currency> | E75: USD | F75: if(terminal_flag, terminal_value, 0) | G75: Calculations!J75:AO75 | J75: =IF(J71,terminal_value,0) -> 0 | K75: =IF(K71,terminal_value,0) -> 0 | L75: =IF(L71,terminal_value,0) -> 0 | M75: =IF(M71,terminal_value,0) -> 0 | N75: =IF(N71,terminal_value,0) -> 0 | O75: =IF(O71,terminal_value,0) -> 0 | P75: =IF(P71,terminal_value,0) -> 0 | Q75: =IF(Q71,terminal_value,0) -> 0 | ... AO75: =IF(AO71,terminal_value,0) -> 1.7804454e+08
A76: valuation_cash_flow | B76: Valuation cash flow (FCF plus TV) | C76: Valuation | D76: series<currency> | E76: USD | F76: free_cash_flow + terminal_value_flow | G76: Calculations!J76:AO76 | J76: =(J48+J75) -> -570877.81 | K76: =(K48+K75) -> -1142947.8 | L76: =(L48+L75) -> -1170788.7 | M76: =(M48+M75) -> -1224810.8 | N76: =(N48+N75) -> -1177363.2 | O76: =(O48+O75) -> -1172451 | P76: =(P48+P75) -> -1139942.4 | Q76: =(Q48+Q75) -> -1077059.5 | ... AO76: =(AO48+AO75) -> 1.8420009e+08
A77: npv_value | B77: NPV | C77: Valuation | D77: currency | E77: USD | F77: npv(discount_rate_q, valuation_cash_flow) | G77: Calculations!I77 | H77: Convention: period t discounted by (1 + r)^t, t from 1 (Excel NPV). Valued at start of period 1. | I77: =NPV(discount_rate_q,$J76:$AO76) -> 51239655
A78: discount_factor_q | B78: Discount factor | C78: Valuation | D78: series<float> | E78: factor | F78: discount_factor(discount_rate_q) | G78: Calculations!J78:AO78 | H78: 1 / (1 + r)^t. | J78: =1/(1+discount_rate_q)^Timeline!J$9 -> 0.9594658 | K78: =1/(1+discount_rate_q)^Timeline!K$9 -> 0.92057462 | L78: =1/(1+discount_rate_q)^Timeline!L$9 -> 0.88325986 | M78: =1/(1+discount_rate_q)^Timeline!M$9 -> 0.84745763 | N78: =1/(1+discount_rate_q)^Timeline!N$9 -> 0.81310661 | O78: =1/(1+discount_rate_q)^Timeline!O$9 -> 0.78014798 | P78: =1/(1+discount_rate_q)^Timeline!P$9 -> 0.74852531 | Q78: =1/(1+discount_rate_q)^Timeline!Q$9 -> 0.71818443 | ... AO78: =1/(1+discount_rate_q)^Timeline!AO$9 -> 0.26603816
A79: pv_valuation_cash_flow | B79: PV of valuation cash flow | C79: Valuation | D79: series<currency> | E79: USD | F79: valuation_cash_flow * discount_factor_q | G79: Calculations!J79:AO79 | J79: =(J76*J78) -> -547737.73 | K79: =(K76*K78) -> -1052168.7 | L79: =(L76*L78) -> -1034110.6 | M79: =(M76*M78) -> -1037975.2 | N79: =(N76*N78) -> -957321.77 | O79: =(O76*O78) -> -914685.27 | P79: =(P76*P78) -> -853275.71 | Q79: =(Q76*Q78) -> -773527.4 | ... AO79: =(AO76*AO78) -> 49004254
A80: npv_check | B80: NPV via discount factors | C80: Valuation | D80: currency | E80: USD | F80: total(pv_valuation_cash_flow) | G80: Calculations!I80 | H80: Must equal npv_value; pins the NPV timing convention. | I80: =SUM($J79:$AO79) -> 51239655
A81: irr_quarterly | B81: IRR (quarterly) | C81: Valuation | D81: percent | E81: fraction | F81: irr(valuation_cash_flow, irr_guess_q) | G81: Calculations!I81 | I81: =IRR($J76:$AO76,irr_guess_q) -> 0.11284888
A82: irr_annual | B82: IRR (annualized) | C82: Valuation | D82: percent | E82: fraction | F82: pow(1 + irr_quarterly, 4) - 1 | G82: Calculations!I82 | I82: =(POWER((1+irr_quarterly),4)-1) -> 0.53371537

Sheet Annual
A1: id | B1: label | C1: type | D1: unit | E1: formula | F1: excel_ref | G1: notes | I1: =MIN(Timeline!$J$12:$AO$12) -> 2027 | J1: =I1+1 -> 2028 | K1: =J1+1 -> 2029 | L1: =K1+1 -> 2030 | M1: =L1+1 -> 2031 | N1: =M1+1 -> 2032 | O1: =N1+1 -> 2033 | P1: =O1+1 -> 2034
A2: fiscal year in row 1 →
A3: revenue_annual | B3: Revenue | C3: annual<currency> | D3: USD | E3: annual(revenue) | F3: Annual!I3:P3 | G3: Sum of the fiscal year's periods; output is on a yearly timeline. | I3: =SUMIF(Timeline!$J$12:$AO$12,I$1,Calculations!$J18:$AO18) -> 11119609 | J3: =SUMIF(Timeline!$J$12:$AO$12,J$1,Calculations!$J18:$AO18) -> 15729006 | K3: =SUMIF(Timeline!$J$12:$AO$12,K$1,Calculations!$J18:$AO18) -> 22526372 | L3: =SUMIF(Timeline!$J$12:$AO$12,L$1,Calculations!$J18:$AO18) -> 31398179 | M3: =SUMIF(Timeline!$J$12:$AO$12,M$1,Calculations!$J18:$AO18) -> 42143879 | N3: =SUMIF(Timeline!$J$12:$AO$12,N$1,Calculations!$J18:$AO18) -> 53953822 | O3: =SUMIF(Timeline!$J$12:$AO$12,O$1,Calculations!$J18:$AO18) -> 66544269 | P3: =SUMIF(Timeline!$J$12:$AO$12,P$1,Calculations!$J18:$AO18) -> 79937672
A4: ebitda_annual | B4: EBITDA | C4: annual<currency> | D4: USD | E4: annual(ebitda) | F4: Annual!I4:P4 | G4: Sum of the fiscal year's periods; output is on a yearly timeline. | I4: =SUMIF(Timeline!$J$12:$AO$12,I$1,Calculations!$J32:$AO32) -> -3046330.3 | J4: =SUMIF(Timeline!$J$12:$AO$12,J$1,Calculations!$J32:$AO32) -> -3564445.5 | K4: =SUMIF(Timeline!$J$12:$AO$12,K$1,Calculations!$J32:$AO32) -> -8442842.2 | L4: =SUMIF(Timeline!$J$12:$AO$12,L$1,Calculations!$J32:$AO32) -> 990715.71 | M4: =SUMIF(Timeline!$J$12:$AO$12,M$1,Calculations!$J32:$AO32) -> 6772317.1 | N4: =SUMIF(Timeline!$J$12:$AO$12,N$1,Calculations!$J32:$AO32) -> 14204731 | O4: =SUMIF(Timeline!$J$12:$AO$12,O$1,Calculations!$J32:$AO32) -> 22305074 | P4: =SUMIF(Timeline!$J$12:$AO$12,P$1,Calculations!$J32:$AO32) -> 31090713
A5: free_cash_flow_annual | B5: Free cash flow | C5: annual<currency> | D5: USD | E5: annual(free_cash_flow) | F5: Annual!I5:P5 | G5: Sum of the fiscal year's periods; output is on a yearly timeline. | I5: =SUMIF(Timeline!$J$12:$AO$12,I$1,Calculations!$J48:$AO48) -> -4109425 | J5: =SUMIF(Timeline!$J$12:$AO$12,J$1,Calculations!$J48:$AO48) -> -4566816.1 | K5: =SUMIF(Timeline!$J$12:$AO$12,K$1,Calculations!$J48:$AO48) -> -12063147 | L5: =SUMIF(Timeline!$J$12:$AO$12,L$1,Calculations!$J48:$AO48) -> -283407.55 | M5: =SUMIF(Timeline!$J$12:$AO$12,M$1,Calculations!$J48:$AO48) -> 5401441.1 | N5: =SUMIF(Timeline!$J$12:$AO$12,N$1,Calculations!$J48:$AO48) -> 12687859 | O5: =SUMIF(Timeline!$J$12:$AO$12,O$1,Calculations!$J48:$AO48) -> 16261695 | P5: =SUMIF(Timeline!$J$12:$AO$12,P$1,Calculations!$J48:$AO48) -> 22005995
A6: new_customers_annual | B6: New customers | C6: annual<quantity> | D6: customers | E6: annual(new_customers) | F6: Annual!I6:P6 | G6: Sum of the fiscal year's periods; output is on a yearly timeline. | I6: =SUMIF(Timeline!$J$12:$AO$12,I$1,Calculations!$J5:$AO5) -> 200 | J6: =SUMIF(Timeline!$J$12:$AO$12,J$1,Calculations!$J5:$AO5) -> 307 | K6: =SUMIF(Timeline!$J$12:$AO$12,K$1,Calculations!$J5:$AO5) -> 413 | L6: =SUMIF(Timeline!$J$12:$AO$12,L$1,Calculations!$J5:$AO5) -> 520 | M6: =SUMIF(Timeline!$J$12:$AO$12,M$1,Calculations!$J5:$AO5) -> 612 | N6: =SUMIF(Timeline!$J$12:$AO$12,N$1,Calculations!$J5:$AO5) -> 676 | O6: =SUMIF(Timeline!$J$12:$AO$12,O$1,Calculations!$J5:$AO5) -> 740 | P6: =SUMIF(Timeline!$J$12:$AO$12,P$1,Calculations!$J5:$AO5) -> 804

Sheet Expected
A1: id | B1: label | C1: type | D1: unit | E1: source | F1: tolerance | G1: role | I1: scalar | J1: 1 | K1: 2 | L1: 3 | M1: 4 | N1: 5 | O1: 6 | P1: 7 | Q1: 8 | R1: 9 | S1: 10 | T1: 11 | U1: 12 | V1: 13 | W1: 14 | X1: 15 | Y1: 16 | Z1: 17 | AA1: 18 | AB1: 19 | AC1: 20 | AD1: 21 | AE1: 22 | AF1: 23 | AG1: 24 | AH1: 25 | AI1: 26 | AJ1: 27 | AK1: 28 | AL1: 29 | AM1: 30 | AN1: 31 | AO1: 32
A2: period label → | J2: =Timeline!J$13 -> 2027Q1 | K2: =Timeline!K$13 -> 2027Q2 | L2: =Timeline!L$13 -> 2027Q3 | M2: =Timeline!M$13 -> 2027Q4 | N2: =Timeline!N$13 -> 2028Q1 | O2: =Timeline!O$13 -> 2028Q2 | P2: =Timeline!P$13 -> 2028Q3 | Q2: =Timeline!Q$13 -> 2028Q4 | ... AO2: =Timeline!AO$13 -> 2034Q4
A3: revenue | B3: Revenue | C3: series<currency> | D3: USD | E3: Calculations!J18:AO18 | F3: rel 1e-6 | G3: required | J3: =Calculations!J18 -> 2472000 | K3: =Calculations!K18 -> 2653657.5 | L3: =Calculations!L18 -> 2870873 | M3: =Calculations!M18 -> 3123079 | N3: =Calculations!N18 -> 3412823.4 | O3: =Calculations!O18 -> 3736419.7 | P3: =Calculations!P18 -> 4093376.9 | Q3: =Calculations!Q18 -> 4486385.9 | ... AO3: =Calculations!AO18 -> 21284873
A4: arr | B4: Annual recurring revenue | C4: series<currency> | D4: USD | E4: Calculations!J17:AO17 | F4: rel 1e-6 | G4: required | J4: =Calculations!J17 -> 10176000 | K4: =Calculations!K17 -> 10977784 | L4: =Calculations!L17 -> 11907777 | M4: =Calculations!M17 -> 12988534 | N4: =Calculations!N17 -> 14217716 | O4: =Calculations!O17 -> 15568188 | P4: =Calculations!P17 -> 17063357 | Q4: =Calculations!Q17 -> 18701170 | ... AO4: =Calculations!AO17 -> 86589185
A5: customers_end | B5: Customers at end of quarter | C5: series<quantity> | D5: customers | E5: Calculations!J8:AO8 | F5: rel 1e-6 | G5: required | J5: =Calculations!J8 -> 424 | K5: =Calculations!K8 -> 454.04 | L5: =Calculations!L8 -> 488.8784 | M5: =Calculations!M8 -> 529.32326 | N5: =Calculations!N8 -> 575.15033 | O5: =Calculations!O8 -> 625.14432 | P5: =Calculations!P8 -> 680.13855 | Q5: =Calculations!Q8 -> 739.93301 | ... AO5: =Calculations!AO8 -> 2869.2205
A6: gross_margin | B6: Gross margin | C6: series<percent> | D6: fraction | E6: Calculations!J24:AO24 | F6: rel 1e-6 | G6: required | J6: =Calculations!J24 -> 0.845 | K6: =Calculations!K24 -> 0.84551537 | L6: =Calculations!L24 -> 0.84602695 | M6: =Calculations!M24 -> 0.84653476 | N6: =Calculations!N24 -> 0.84703883 | O6: =Calculations!O24 -> 0.8475392 | P6: =Calculations!P24 -> 0.84803587 | Q6: =Calculations!Q24 -> 0.8485289 | ... AO6: =Calculations!AO24 -> 0.8593315
A7: ebitda | B7: EBITDA | C7: series<currency> | D7: USD | E7: Calculations!J32:AO32 | F7: rel 1e-6 | G7: required | J7: =Calculations!J32 -> -721160 | K7: =Calculations!K32 -> -736291.83 | L7: =Calculations!L32 -> -766539.09 | M7: =Calculations!M32 -> -822339.4 | N7: =Calculations!N32 -> -926493.76 | O7: =Calculations!O32 -> -922082.75 | P7: =Calculations!P32 -> -889485.63 | Q7: =Calculations!Q32 -> -826383.39 | ... AO7: =Calculations!AO32 -> 8660757.6
A8: free_cash_flow | B8: Free cash flow (unlevered) | C8: series<currency> | D8: USD | E8: Calculations!J48:AO48 | F8: rel 1e-6 | G8: required | J8: =Calculations!J48 -> -570877.81 | K8: =Calculations!K48 -> -1142947.8 | L8: =Calculations!L48 -> -1170788.7 | M8: =Calculations!M48 -> -1224810.8 | N8: =Calculations!N48 -> -1177363.2 | O8: =Calculations!O48 -> -1172451 | P8: =Calculations!P48 -> -1139942.4 | Q8: =Calculations!Q48 -> -1077059.5 | ... AO8: =Calculations!AO48 -> 6155557.3
A9: cash_balance | B9: Cash balance | C9: series<currency> | D9: USD | E9: Calculations!J51:AO51 | F9: rel 1e-6 | G9: required | J9: =Calculations!J51 -> 24429122 | K9: =Calculations!K51 -> 23286174 | L9: =Calculations!L51 -> 22115386 | M9: =Calculations!M51 -> 20890575 | N9: =Calculations!N51 -> 19713212 | O9: =Calculations!O51 -> 48540761 | P9: =Calculations!P51 -> 47400818 | Q9: =Calculations!Q51 -> 46323759 | ... AO9: =Calculations!AO51 -> 1.3033419e+08
A10: npv_value | B10: NPV | C10: currency | D10: USD | E10: Calculations!I77 | F10: rel 1e-6 | G10: required | I10: =Calculations!I77 -> 51239655
A11: irr_annual | B11: IRR (annualized) | C11: percent | D11: fraction | E11: Calculations!I82 | F11: rel 1e-6 | G11: required | I11: =Calculations!I82 -> 0.53371537
A12: ltv_to_cac | B12: Lifetime value to CAC | C12: series<float> | D12: ratio | E12: Calculations!J59:AO59 | F12: rel 1e-6 | G12: required | J12: =Calculations!J59 -> 5.8275862 | K12: =Calculations!K59 -> 6.1908203 | L12: =Calculations!L59 -> 6.1220246 | M12: =Calculations!M59 -> 6.1822232 | N12: =Calculations!N59 -> 6.2406566 | O12: =Calculations!O59 -> 6.2128196 | P12: =Calculations!P59 -> 6.2759808 | Q12: =Calculations!Q59 -> 6.3375948 | ... AO12: =Calculations!AO59 -> 7.6952784
A13: cac_payback_months | B13: CAC payback | C13: series<float> | D13: months | E13: Calculations!J60:AO60 | F13: rel 1e-6 | G13: required | J13: =Calculations!J60 -> 12.869822 | K13: =Calculations!K60 -> 12.114711 | L13: =Calculations!L60 -> 12.250849 | M13: =Calculations!M60 -> 12.131558 | N13: =Calculations!N60 -> 12.017966 | O13: =Calculations!O60 -> 12.071814 | P13: =Calculations!P60 -> 11.950323 | Q13: =Calculations!Q60 -> 11.834143 | ... AO13: =Calculations!AO60 -> 9.7462361
A14: burn_multiple | B14: Burn multiple | C14: series<float> | D14: ratio | E14: Calculations!J65:AO65 | F14: rel 1e-6 | G14: checkpoint | J14: =Calculations!J65 -> 0.056100414 | K14: =Calculations!K65 -> 1.4255067 | L14: =Calculations!L65 -> 1.258921 | M14: =Calculations!M65 -> 1.1332898 | N14: =Calculations!N65 -> 0.95784279 | O14: =Calculations!O65 -> 0.86817894 | P14: =Calculations!P65 -> 0.76241716 | Q14: =Calculations!Q65 -> 0.65762033 | ... AO14: =Calculations!AO65 -> 0
A15: new_customers | B15: New customers | C15: series<quantity> | D15: customers | E15: Calculations!J5:AO5 | F15: rel 1e-6 | G15: checkpoint | J15: =Calculations!J5 -> 40 | K15: =Calculations!K5 -> 47 | L15: =Calculations!L5 -> 53 | M15: =Calculations!M5 -> 60 | N15: =Calculations!N5 -> 67 | O15: =Calculations!O5 -> 73 | P15: =Calculations!P5 -> 80 | Q15: =Calculations!Q5 -> 87 | ... AO15: =Calculations!AO5 -> 207
A16: retention_factor | B16: Share of a period-1 customer still active | C16: series<float> | D16: fraction | E16: Calculations!J6:AO6 | F16: rel 1e-6 | G16: checkpoint | J16: =Calculations!J6 -> 0.96 | K16: =Calculations!K6 -> 0.9216 | L16: =Calculations!L6 -> 0.884736 | M16: =Calculations!M6 -> 0.84934656 | N16: =Calculations!N6 -> 0.8153727 | O16: =Calculations!O6 -> 0.78275779 | P16: =Calculations!P6 -> 0.75144748 | Q16: =Calculations!Q6 -> 0.72138958 | ... AO16: =Calculations!AO6 -> 0.2708192
A17: churned_customers | B17: Customers lost | C17: series<quantity> | D17: customers | E17: Calculations!J10:AO10 | F17: rel 1e-6 | G17: checkpoint | J17: =Calculations!J10 -> 16 | K17: =Calculations!K10 -> 16.96 | L17: =Calculations!L10 -> 18.1616 | M17: =Calculations!M10 -> 19.555136 | N17: =Calculations!N10 -> 21.172931 | O17: =Calculations!O10 -> 23.006013 | P17: =Calculations!P10 -> 25.005773 | Q17: =Calculations!Q10 -> 27.205542 | ... AO17: =Calculations!AO10 -> 110.92585
A18: average_customers | B18: Average customers | C18: series<quantity> | D18: customers | E18: Calculations!J12:AO12 | F18: rel 1e-6 | G18: checkpoint | J18: =Calculations!J12 -> 412 | K18: =Calculations!K12 -> 439.02 | L18: =Calculations!L12 -> 471.4592 | M18: =Calculations!M12 -> 509.10083 | N18: =Calculations!N12 -> 552.2368 | O18: =Calculations!O12 -> 600.14733 | P18: =Calculations!P12 -> 652.64143 | Q18: =Calculations!Q12 -> 710.03578 | ... AO18: =Calculations!AO12 -> 2821.1834
A19: price_index | B19: Price index | C19: series<float> | D19: index | E19: Calculations!J14:AO14 | F19: rel 1e-6 | G19: checkpoint | J19: =Calculations!J14 -> 1 | K19: =Calculations!K14 -> 1.0074171 | L19: =Calculations!L14 -> 1.0148892 | M19: =Calculations!M14 -> 1.0224167 | N19: =Calculations!N14 -> 1.03 | O19: =Calculations!O14 -> 1.0376396 | P19: =Calculations!P14 -> 1.0453358 | Q19: =Calculations!Q14 -> 1.0530892 | ... AO19: =Calculations!AO14 -> 1.2574435
A20: cogs_total | B20: Cost of revenue | C20: series<currency> | D20: USD | E20: Calculations!J22:AO22 | F20: rel 1e-6 | G20: checkpoint | J20: =Calculations!J22 -> 383160 | K20: =Calculations!K22 -> 409949.28 | L20: =Calculations!L22 -> 442037.07 | M20: =Calculations!M22 -> 479284.07 | N20: =Calculations!N22 -> 522029.45 | O20: =Calculations!O22 -> 569657.55 | P20: =Calculations!P22 -> 622046.43 | Q20: =Calculations!Q22 -> 679557.83 | ... AO20: =Calculations!AO22 -> 2994111.2
A21: opex_total | B21: Operating expenses | C21: series<currency> | D21: USD | E21: Calculations!J31:AO31 | F21: rel 1e-6 | G21: checkpoint | J21: =Calculations!J31 -> 2810000 | K21: =Calculations!K31 -> 2980000 | L21: =Calculations!L31 -> 3195375 | M21: =Calculations!M31 -> 3466134.4 | N21: =Calculations!N31 -> 3817287.7 | O21: =Calculations!O31 -> 4088844.9 | P21: =Calculations!P31 -> 4360816.1 | Q21: =Calculations!Q31 -> 4633211.5 | ... AO21: =Calculations!AO31 -> 9630004.1
A22: depreciation | B22: Depreciation | C22: series<currency> | D22: USD | E22: Calculations!J36:AO36 | F22: rel 1e-6 | G22: checkpoint | J22: =Calculations!J36 -> 36423.333 | K22: =Calculations!K36 -> 73073.738 | L22: =Calculations!L36 -> 109995.66 | M22: =Calculations!M36 -> 147232.85 | N22: =Calculations!N36 -> 172332.21 | O22: =Calculations!O36 -> 197836.07 | P22: =Calculations!P36 -> 223786.12 | Q22: =Calculations!Q36 -> 250227.44 | ... AO22: =Calculations!AO36 -> 550544.7
A23: tax | B23: Income tax | C23: series<currency> | D23: USD | E23: Calculations!J41:AO41 | F23: rel 1e-6 | G23: checkpoint | J23: =Calculations!J41 -> 0 | K23: =Calculations!K41 -> 0 | L23: =Calculations!L41 -> 0 | M23: =Calculations!M41 -> 0 | N23: =Calculations!N41 -> 0 | O23: =Calculations!O41 -> 0 | P23: =Calculations!P41 -> 0 | Q23: =Calculations!Q41 -> 0 | ... AO23: =Calculations!AO41 -> 2027553.2
A24: change_in_nwc | B24: Change in net working capital | C24: series<currency> | D24: USD | E24: Calculations!J47:AO47 | F24: rel 1e-6 | G24: checkpoint | J24: =Calculations!J47 -> -587362.19 | K24: =Calculations!K47 -> -33148.918 | L24: =Calculations!L47 -> -38813.532 | M24: =Calculations!M47 -> -44374.799 | N24: =Calculations!N47 -> -50322.957 | O24: =Calculations!O47 -> -55678.062 | P24: =Calculations!P47 -> -60943.912 | Q24: =Calculations!Q47 -> -66619.637 | ... AO24: =Calculations!AO47 -> -141626
A25: npv_check | B25: NPV via discount factors | C25: currency | D25: USD | E25: Calculations!I80 | F25: rel 1e-6 | G25: checkpoint | I25: =Calculations!I80 -> 51239655
A26: irr_quarterly | B26: IRR (quarterly) | C26: percent | D26: fraction | E26: Calculations!I81 | F26: rel 1e-6 | G26: checkpoint | I26: =Calculations!I81 -> 0.11284888
A27: terminal_value | B27: Terminal value (Gordon growth) | C27: currency | D27: USD | E27: Calculations!I74 | F27: rel 1e-6 | G27: checkpoint | I27: =Calculations!I74 -> 1.7804454e+08
A28: cash_above_minimum | B28: Cash above minimum | C28: series<bool> | D28: flag | E28: Calculations!J52:AO52 | F28: exact | G28: checkpoint | J28: =Calculations!J52 -> TRUE | K28: =Calculations!K52 -> TRUE | L28: =Calculations!L52 -> TRUE | M28: =Calculations!M52 -> TRUE | N28: =Calculations!N52 -> TRUE | O28: =Calculations!O52 -> TRUE | P28: =Calculations!P52 -> TRUE | Q28: =Calculations!Q52 -> TRUE | ... AO28: =Calculations!AO52 -> TRUE
A29: rule_of_40_met | B29: Rule of 40 met | C29: series<bool> | D29: flag | E29: Calculations!J63:AO63 | F29: exact | G29: checkpoint | J29: =Calculations!J63 -> FALSE | K29: =Calculations!K63 -> FALSE | L29: =Calculations!L63 -> FALSE | M29: =Calculations!M63 -> FALSE | N29: =Calculations!N63 -> FALSE | O29: =Calculations!O63 -> FALSE | P29: =Calculations!P63 -> FALSE | Q29: =Calculations!Q63 -> FALSE | ... AO29: =Calculations!AO63 -> TRUE
A30: customers_won_total | B30: Customers won, total | C30: quantity | D30: customers | E30: Calculations!I68 | F30: rel 1e-6 | G30: checkpoint | I30: =Calculations!I68 -> 4272

Sheet Expected_Annual
A1: id | B1: label | C1: type | D1: unit | E1: source | F1: tolerance | G1: role | I1: =Annual!I1 -> 2027 | J1: =Annual!J1 -> 2028 | K1: =Annual!K1 -> 2029 | L1: =Annual!L1 -> 2030 | M1: =Annual!M1 -> 2031 | N1: =Annual!N1 -> 2032 | O1: =Annual!O1 -> 2033 | P1: =Annual!P1 -> 2034
A3: revenue_annual | B3: Revenue | C3: annual<currency> | D3: USD | E3: Annual!I3:P3 | F3: rel 1e-6 | G3: checkpoint | I3: =Annual!I3 -> 11119609 | J3: =Annual!J3 -> 15729006 | K3: =Annual!K3 -> 22526372 | L3: =Annual!L3 -> 31398179 | M3: =Annual!M3 -> 42143879 | N3: =Annual!N3 -> 53953822 | O3: =Annual!O3 -> 66544269 | P3: =Annual!P3 -> 79937672
A4: ebitda_annual | B4: EBITDA | C4: annual<currency> | D4: USD | E4: Annual!I4:P4 | F4: rel 1e-6 | G4: checkpoint | I4: =Annual!I4 -> -3046330.3 | J4: =Annual!J4 -> -3564445.5 | K4: =Annual!K4 -> -8442842.2 | L4: =Annual!L4 -> 990715.71 | M4: =Annual!M4 -> 6772317.1 | N4: =Annual!N4 -> 14204731 | O4: =Annual!O4 -> 22305074 | P4: =Annual!P4 -> 31090713
A5: free_cash_flow_annual | B5: Free cash flow | C5: annual<currency> | D5: USD | E5: Annual!I5:P5 | F5: rel 1e-6 | G5: checkpoint | I5: =Annual!I5 -> -4109425 | J5: =Annual!J5 -> -4566816.1 | K5: =Annual!K5 -> -12063147 | L5: =Annual!L5 -> -283407.55 | M5: =Annual!M5 -> 5401441.1 | N5: =Annual!N5 -> 12687859 | O5: =Annual!O5 -> 16261695 | P5: =Annual!P5 -> 22005995
A6: new_customers_annual | B6: New customers | C6: annual<quantity> | D6: customers | E6: Annual!I6:P6 | F6: rel 1e-6 | G6: checkpoint | I6: =Annual!I6 -> 200 | J6: =Annual!J6 -> 307 | K6: =Annual!K6 -> 413 | L6: =Annual!L6 -> 520 | M6: =Annual!M6 -> 612 | N6: =Annual!N6 -> 676 | O6: =Annual!O6 -> 740 | P6: =Annual!P6 -> 804

Sheet Report
A1: order | B1: id | C1: label | D1: format | E1: source | I1: scalar | J1: 1 | K1: 2 | L1: 3 | M1: 4 | N1: 5 | O1: 6 | P1: 7 | Q1: 8 | R1: 9 | S1: 10 | T1: 11 | U1: 12 | V1: 13 | W1: 14 | X1: 15 | Y1: 16 | Z1: 17 | AA1: 18 | AB1: 19 | AC1: 20 | AD1: 21 | AE1: 22 | AF1: 23 | AG1: 24 | AH1: 25 | AI1: 26 | AJ1: 27 | AK1: 28 | AL1: 29 | AM1: 30 | AN1: 31 | AO1: 32
A2: period label → | J2: =Timeline!J$13 -> 2027Q1 | K2: =Timeline!K$13 -> 2027Q2 | L2: =Timeline!L$13 -> 2027Q3 | M2: =Timeline!M$13 -> 2027Q4 | N2: =Timeline!N$13 -> 2028Q1 | O2: =Timeline!O$13 -> 2028Q2 | P2: =Timeline!P$13 -> 2028Q3 | Q2: =Timeline!Q$13 -> 2028Q4 | ... AO2: =Timeline!AO$13 -> 2034Q4
A3: 1 | B3: customers_end | C3: Customers at end of quarter | D3: #,##0 | E3: Calculations!J8:AO8 | J3: =Calculations!J8 -> 424 | K3: =Calculations!K8 -> 454.04 | L3: =Calculations!L8 -> 488.8784 | M3: =Calculations!M8 -> 529.32326 | N3: =Calculations!N8 -> 575.15033 | O3: =Calculations!O8 -> 625.14432 | P3: =Calculations!P8 -> 680.13855 | Q3: =Calculations!Q8 -> 739.93301 | ... AO3: =Calculations!AO8 -> 2869.2205
A4: 2 | B4: new_customers | C4: New customers | D4: #,##0 | E4: Calculations!J5:AO5 | J4: =Calculations!J5 -> 40 | K4: =Calculations!K5 -> 47 | L4: =Calculations!L5 -> 53 | M4: =Calculations!M5 -> 60 | N4: =Calculations!N5 -> 67 | O4: =Calculations!O5 -> 73 | P4: =Calculations!P5 -> 80 | Q4: =Calculations!Q5 -> 87 | ... AO4: =Calculations!AO5 -> 207
A5: 3 | B5: churned_customers | C5: Customers lost | D5: #,##0 | E5: Calculations!J10:AO10 | J5: =Calculations!J10 -> 16 | K5: =Calculations!K10 -> 16.96 | L5: =Calculations!L10 -> 18.1616 | M5: =Calculations!M10 -> 19.555136 | N5: =Calculations!N10 -> 21.172931 | O5: =Calculations!O10 -> 23.006013 | P5: =Calculations!P10 -> 25.005773 | Q5: =Calculations!Q10 -> 27.205542 | ... AO5: =Calculations!AO10 -> 110.92585
A6: 4 | B6: arr | C6: Annual recurring revenue | D6: $#,##0 | E6: Calculations!J17:AO17 | J6: =Calculations!J17 -> 10176000 | K6: =Calculations!K17 -> 10977784 | L6: =Calculations!L17 -> 11907777 | M6: =Calculations!M17 -> 12988534 | N6: =Calculations!N17 -> 14217716 | O6: =Calculations!O17 -> 15568188 | P6: =Calculations!P17 -> 17063357 | Q6: =Calculations!Q17 -> 18701170 | ... AO6: =Calculations!AO17 -> 86589185
A7: 5 | B7: revenue | C7: Revenue | D7: $#,##0 | E7: Calculations!J18:AO18 | J7: =Calculations!J18 -> 2472000 | K7: =Calculations!K18 -> 2653657.5 | L7: =Calculations!L18 -> 2870873 | M7: =Calculations!M18 -> 3123079 | N7: =Calculations!N18 -> 3412823.4 | O7: =Calculations!O18 -> 3736419.7 | P7: =Calculations!P18 -> 4093376.9 | Q7: =Calculations!Q18 -> 4486385.9 | ... AO7: =Calculations!AO18 -> 21284873
A8: 6 | B8: cogs_total | C8: Cost of revenue | D8: $#,##0 | E8: Calculations!J22:AO22 | J8: =Calculations!J22 -> 383160 | K8: =Calculations!K22 -> 409949.28 | L8: =Calculations!L22 -> 442037.07 | M8: =Calculations!M22 -> 479284.07 | N8: =Calculations!N22 -> 522029.45 | O8: =Calculations!O22 -> 569657.55 | P8: =Calculations!P22 -> 622046.43 | Q8: =Calculations!Q22 -> 679557.83 | ... AO8: =Calculations!AO22 -> 2994111.2
A9: 7 | B9: gross_profit | C9: Gross profit | D9: $#,##0 | E9: Calculations!J23:AO23 | J9: =Calculations!J23 -> 2088840 | K9: =Calculations!K23 -> 2243708.2 | L9: =Calculations!L23 -> 2428835.9 | M9: =Calculations!M23 -> 2643795 | N9: =Calculations!N23 -> 2890794 | O9: =Calculations!O23 -> 3166762.2 | P9: =Calculations!P23 -> 3471330.4 | Q9: =Calculations!Q23 -> 3806828.1 | ... AO9: =Calculations!AO23 -> 18290762
A10: 8 | B10: gross_margin | C10: Gross margin | D10: 0.0% | E10: Calculations!J24:AO24 | J10: =Calculations!J24 -> 0.845 | K10: =Calculations!K24 -> 0.84551537 | L10: =Calculations!L24 -> 0.84602695 | M10: =Calculations!M24 -> 0.84653476 | N10: =Calculations!N24 -> 0.84703883 | O10: =Calculations!O24 -> 0.8475392 | P10: =Calculations!P24 -> 0.84803587 | Q10: =Calculations!Q24 -> 0.8485289 | ... AO10: =Calculations!AO24 -> 0.8593315
A11: 9 | B11: sales_marketing | C11: Sales and marketing | D11: $#,##0 | E11: Calculations!J26:AO26 | J11: =Calculations!J26 -> 870000 | K11: =Calculations!K26 -> 970000 | L11: =Calculations!L26 -> 1115000 | M11: =Calculations!M26 -> 1260000 | N11: =Calculations!N26 -> 1405000 | O11: =Calculations!O26 -> 1550000 | P11: =Calculations!P26 -> 1695000 | Q11: =Calculations!Q26 -> 1840000 | ... AO11: =Calculations!AO26 -> 4360000
A12: 10 | B12: research_development | C12: Research and development | D12: $#,##0 | E12: Calculations!J27:AO27 | J12: =Calculations!J27 -> 1100000 | K12: =Calculations!K27 -> 1155000 | L12: =Calculations!L27 -> 1210000 | M12: =Calculations!M27 -> 1320000 | N12: =Calculations!N27 -> 1430000 | O12: =Calculations!O27 -> 1540000 | P12: =Calculations!P27 -> 1650000 | Q12: =Calculations!Q27 -> 1760000 | ... AO12: =Calculations!AO27 -> 3300000
A13: 11 | B13: general_admin | C13: General and administrative | D13: $#,##0 | E13: Calculations!J29:AO29 | J13: =Calculations!J29 -> 840000 | K13: =Calculations!K29 -> 855000 | L13: =Calculations!L29 -> 870375 | M13: =Calculations!M29 -> 886134.38 | N13: =Calculations!N29 -> 982287.73 | O13: =Calculations!O29 -> 998844.93 | P13: =Calculations!P29 -> 1015816.1 | Q13: =Calculations!Q29 -> 1033211.5 | ... AO13: =Calculations!AO29 -> 1970004.1
A14: 12 | B14: opex_total | C14: Operating expenses | D14: $#,##0 | E14: Calculations!J31:AO31 | J14: =Calculations!J31 -> 2810000 | K14: =Calculations!K31 -> 2980000 | L14: =Calculations!L31 -> 3195375 | M14: =Calculations!M31 -> 3466134.4 | N14: =Calculations!N31 -> 3817287.7 | O14: =Calculations!O31 -> 4088844.9 | P14: =Calculations!P31 -> 4360816.1 | Q14: =Calculations!Q31 -> 4633211.5 | ... AO14: =Calculations!AO31 -> 9630004.1
A15: 13 | B15: ebitda | C15: EBITDA | D15: $#,##0 | E15: Calculations!J32:AO32 | J15: =Calculations!J32 -> -721160 | K15: =Calculations!K32 -> -736291.83 | L15: =Calculations!L32 -> -766539.09 | M15: =Calculations!M32 -> -822339.4 | N15: =Calculations!N32 -> -926493.76 | O15: =Calculations!O32 -> -922082.75 | P15: =Calculations!P32 -> -889485.63 | Q15: =Calculations!Q32 -> -826383.39 | ... AO15: =Calculations!AO32 -> 8660757.6
A16: 14 | B16: ebitda_margin | C16: EBITDA margin | D16: 0.0% | E16: Calculations!J33:AO33 | J16: =Calculations!J33 -> -0.29173139 | K16: =Calculations!K33 -> -0.27746303 | L16: =Calculations!L33 -> -0.26700557 | M16: =Calculations!M33 -> -0.26331047 | N16: =Calculations!N33 -> -0.27147428 | O16: =Calculations!O33 -> -0.24678243 | P16: =Calculations!P33 -> -0.21729874 | Q16: =Calculations!Q33 -> -0.18419802 | ... AO16: =Calculations!AO33 -> 0.40689731
A17: 15 | B17: depreciation | C17: Depreciation | D17: $#,##0 | E17: Calculations!J36:AO36 | J17: =Calculations!J36 -> 36423.333 | K17: =Calculations!K36 -> 73073.738 | L17: =Calculations!L36 -> 109995.66 | M17: =Calculations!M36 -> 147232.85 | N17: =Calculations!N36 -> 172332.21 | O17: =Calculations!O36 -> 197836.07 | P17: =Calculations!P36 -> 223786.12 | Q17: =Calculations!Q36 -> 250227.44 | ... AO17: =Calculations!AO36 -> 550544.7
A18: 16 | B18: ebit | C18: EBIT | D18: $#,##0 | E18: Calculations!J37:AO37 | J18: =Calculations!J37 -> -757583.33 | K18: =Calculations!K37 -> -809365.57 | L18: =Calculations!L37 -> -876534.75 | M18: =Calculations!M37 -> -969572.25 | N18: =Calculations!N37 -> -1098826 | O18: =Calculations!O37 -> -1119918.8 | P18: =Calculations!P37 -> -1113271.8 | Q18: =Calculations!Q37 -> -1076610.8 | ... AO18: =Calculations!AO37 -> 8110212.9
A19: 17 | B19: tax | C19: Income tax | D19: $#,##0 | E19: Calculations!J41:AO41 | J19: =Calculations!J41 -> 0 | K19: =Calculations!K41 -> 0 | L19: =Calculations!L41 -> 0 | M19: =Calculations!M41 -> 0 | N19: =Calculations!N41 -> 0 | O19: =Calculations!O41 -> 0 | P19: =Calculations!P41 -> 0 | Q19: =Calculations!Q41 -> 0 | ... AO19: =Calculations!AO41 -> 2027553.2
A20: 18 | B20: net_income | C20: Net income | D20: $#,##0 | E20: Calculations!J42:AO42 | J20: =Calculations!J42 -> -757583.33 | K20: =Calculations!K42 -> -809365.57 | L20: =Calculations!L42 -> -876534.75 | M20: =Calculations!M42 -> -969572.25 | N20: =Calculations!N42 -> -1098826 | O20: =Calculations!O42 -> -1119918.8 | P20: =Calculations!P42 -> -1113271.8 | Q20: =Calculations!Q42 -> -1076610.8 | ... AO20: =Calculations!AO42 -> 6082659.7
A21: 19 | B21: capex_total | C21: Capex | D21: $#,##0 | E21: Calculations!J35:AO35 | J21: =Calculations!J35 -> 437080 | K21: =Calculations!K35 -> 439804.86 | L21: =Calculations!L35 -> 443063.09 | M21: =Calculations!M35 -> 446846.19 | N21: =Calculations!N35 -> 301192.35 | O21: =Calculations!O35 -> 306046.3 | P21: =Calculations!P35 -> 311400.65 | Q21: =Calculations!Q35 -> 317295.79 | ... AO21: =Calculations!AO35 -> 619273.09
A22: 20 | B22: change_in_nwc | C22: Change in net working capital | D22: $#,##0 | E22: Calculations!J47:AO47 | J22: =Calculations!J47 -> -587362.19 | K22: =Calculations!K47 -> -33148.918 | L22: =Calculations!L47 -> -38813.532 | M22: =Calculations!M47 -> -44374.799 | N22: =Calculations!N47 -> -50322.957 | O22: =Calculations!O47 -> -55678.062 | P22: =Calculations!P47 -> -60943.912 | Q22: =Calculations!Q47 -> -66619.637 | ... AO22: =Calculations!AO47 -> -141626
A23: 21 | B23: free_cash_flow | C23: Free cash flow (unlevered) | D23: $#,##0 | E23: Calculations!J48:AO48 | J23: =Calculations!J48 -> -570877.81 | K23: =Calculations!K48 -> -1142947.8 | L23: =Calculations!L48 -> -1170788.7 | M23: =Calculations!M48 -> -1224810.8 | N23: =Calculations!N48 -> -1177363.2 | O23: =Calculations!O48 -> -1172451 | P23: =Calculations!P48 -> -1139942.4 | Q23: =Calculations!Q48 -> -1077059.5 | ... AO23: =Calculations!AO48 -> 6155557.3
A24: 22 | B24: equity_raises | C24: Equity raised | D24: $#,##0 | E24: Driver_Series!J8:AO8 | J24: =Driver_Series!J8 -> 0 | K24: =Driver_Series!K8 -> 0 | L24: =Driver_Series!L8 -> 0 | M24: =Driver_Series!M8 -> 0 | N24: =Driver_Series!N8 -> 0 | O24: =Driver_Series!O8 -> 30000000 | P24: =Driver_Series!P8 -> 0 | Q24: =Driver_Series!Q8 -> 0 | ... AO24: =Driver_Series!AO8 -> 0
A25: 23 | B25: cash_balance | C25: Cash balance | D25: $#,##0 | E25: Calculations!J51:AO51 | J25: =Calculations!J51 -> 24429122 | K25: =Calculations!K51 -> 23286174 | L25: =Calculations!L51 -> 22115386 | M25: =Calculations!M51 -> 20890575 | N25: =Calculations!N51 -> 19713212 | O25: =Calculations!O51 -> 48540761 | P25: =Calculations!P51 -> 47400818 | Q25: =Calculations!Q51 -> 46323759 | ... AO25: =Calculations!AO51 -> 1.3033419e+08
A26: 24 | B26: runway_quarters | C26: Runway at current burn | D26: #,##0.0 | E26: Calculations!J54:AO54 | J26: =Calculations!J54 -> 42.792208 | K26: =Calculations!K54 -> 20.373787 | L26: =Calculations!L54 -> 18.889307 | M26: =Calculations!M54 -> 17.056165 | N26: =Calculations!N54 -> 16.743527 | O26: =Calculations!O54 -> 41.4011 | P26: =Calculations!P54 -> 41.581767 | Q26: =Calculations!Q54 -> 43.009469 | ... AO26: =Calculations!AO54 -> 0
A27: 25 | B27: cac_fully_loaded | C27: Customer acquisition cost (fully loaded) | D27: $#,##0 | E27: Calculations!J55:AO55 | J27: =Calculations!J55 -> 21750 | K27: =Calculations!K55 -> 20638.298 | L27: =Calculations!L55 -> 21037.736 | M27: =Calculations!M55 -> 21000 | N27: =Calculations!N55 -> 20970.149 | O27: =Calculations!O55 -> 21232.877 | P27: =Calculations!P55 -> 21187.5 | Q27: =Calculations!Q55 -> 21149.425 | ... AO27: =Calculations!AO55 -> 21062.802
A28: 26 | B28: ltv_to_cac | C28: Lifetime value to CAC | D28: 0.0 | E28: Calculations!J59:AO59 | J28: =Calculations!J59 -> 5.8275862 | K28: =Calculations!K59 -> 6.1908203 | L28: =Calculations!L59 -> 6.1220246 | M28: =Calculations!M59 -> 6.1822232 | N28: =Calculations!N59 -> 6.2406566 | O28: =Calculations!O59 -> 6.2128196 | P28: =Calculations!P59 -> 6.2759808 | Q28: =Calculations!Q59 -> 6.3375948 | ... AO28: =Calculations!AO59 -> 7.6952784
A29: 27 | B29: cac_payback_months | C29: CAC payback | D29: #,##0.0 | E29: Calculations!J60:AO60 | J29: =Calculations!J60 -> 12.869822 | K29: =Calculations!K60 -> 12.114711 | L29: =Calculations!L60 -> 12.250849 | M29: =Calculations!M60 -> 12.131558 | N29: =Calculations!N60 -> 12.017966 | O29: =Calculations!O60 -> 12.071814 | P29: =Calculations!P60 -> 11.950323 | Q29: =Calculations!Q60 -> 11.834143 | ... AO29: =Calculations!AO60 -> 9.7462361
A30: 28 | B30: rule_of_40 | C30: Rule of 40 score | D30: 0.0% | E30: Calculations!J62:AO62 | J30: =Calculations!J62 -> -0.29173139 | K30: =Calculations!K62 -> -0.27746303 | L30: =Calculations!L62 -> -0.26700557 | M30: =Calculations!M62 -> -0.26331047 | N30: =Calculations!N62 -> 0.10911772 | O30: =Calculations!O62 -> 0.16124396 | P30: =Calculations!P62 -> 0.20853127 | Q30: =Calculations!Q62 -> 0.25232851 | ... AO30: =Calculations!AO62 -> 0.59866438
A31: 29 | B31: npv_value | C31: NPV | D31: $#,##0 | E31: Calculations!I77 | I31: =Calculations!I77 -> 51239655
A32: 30 | B32: irr_annual | C32: IRR (annualized) | D32: 0.0% | E32: Calculations!I82 | I32: =Calculations!I82 -> 0.53371537
